{
  "patches": {
    "@/main": {
      "links": {
        "H125GIyMt": {
          "id": "H125GIyMt",
          "output": {
            "nodeId": "H10Kf81zt",
            "pinKey": "r1if8ROSDJ-"
          },
          "input": {
            "nodeId": "r17aXNjbt",
            "pinKey": "HJ6HsEngZ"
          }
        },
        "rJ-iGLJGt": {
          "id": "rJ-iGLJGt",
          "output": {
            "nodeId": "S1NbRH1fF",
            "pinKey": "HkU3vNoTW"
          },
          "input": {
            "nodeId": "H10Kf81zt",
            "pinKey": "ry3zLA_Bv1Z"
          }
        },
        "S1ZgiXL1MY": {
          "id": "S1ZgiXL1MY",
          "output": {
            "nodeId": "SygsQUyzt",
            "pinKey": "HkU3vNoTW"
          },
          "input": {
            "nodeId": "H1gejmI1zF",
            "pinKey": "ry3zLA_Bv1Z"
          }
        },
        "S1brj7IkzK": {
          "id": "S1brj7IkzK",
          "output": {
            "nodeId": "SJSiQ8JzF",
            "pinKey": "HkU3vNoTW"
          },
          "input": {
            "nodeId": "rylro7L1GK",
            "pinKey": "ry3zLA_Bv1Z"
          }
        },
        "B1busQI1GK": {
          "id": "B1busQI1GK",
          "output": {
            "nodeId": "Sk_smIkGY",
            "pinKey": "HkU3vNoTW"
          },
          "input": {
            "nodeId": "SJeuiQ81Gt",
            "pinKey": "ry3zLA_Bv1Z"
          }
        },
        "r1Chm8kMt": {
          "id": "r1Chm8kMt",
          "output": {
            "nodeId": "H1gejmI1zF",
            "pinKey": "r1if8ROSDJ-"
          },
          "input": {
            "nodeId": "BkgC14VoZF",
            "pinKey": "HJ6HsEngZ"
          }
        },
        "Bkx6X81GF": {
          "id": "Bkx6X81GF",
          "output": {
            "nodeId": "rylro7L1GK",
            "pinKey": "r1if8ROSDJ-"
          },
          "input": {
            "nodeId": "ryxplENiZt",
            "pinKey": "HJ6HsEngZ"
          }
        },
        "BJWaQLyzY": {
          "id": "BJWaQLyzY",
          "output": {
            "nodeId": "SJeuiQ81Gt",
            "pinKey": "r1if8ROSDJ-"
          },
          "input": {
            "nodeId": "HyM6g44jbY",
            "pinKey": "HJ6HsEngZ"
          }
        },
        "r1SxNI1zt": {
          "id": "r1SxNI1zt",
          "output": {
            "nodeId": "BkzxNL1ft",
            "pinKey": "ByHmL0uHPk-"
          },
          "input": {
            "nodeId": "S1NbRH1fF",
            "pinKey": "SkSuD6LMb"
          }
        },
        "HJtl48JGt": {
          "id": "HJtl48JGt",
          "output": {
            "nodeId": "ry-yNIJzt",
            "pinKey": "HJhXDIY9-"
          },
          "input": {
            "nodeId": "BkzxNL1ft",
            "pinKey": "ryv7IRdSP1b"
          }
        },
        "r1WbVL1fY": {
          "id": "r1WbVL1fY",
          "output": {
            "nodeId": "rkAeEL1Gt",
            "pinKey": "ryVmUAOrvkb"
          },
          "input": {
            "nodeId": "BkzxNL1ft",
            "pinKey": "ByU7LRuSPkW"
          }
        },
        "S14mBF7MF": {
          "id": "S14mBF7MF",
          "output": {
            "nodeId": "B1lXHFQGK",
            "pinKey": "B1x2RV3eZ"
          },
          "input": {
            "nodeId": "ByEzHY7MY",
            "pinKey": "r1AgIROHDJW"
          }
        },
        "BJI7HKXGY": {
          "id": "BJI7HKXGY",
          "output": {
            "nodeId": "SkMeHtQGY",
            "pinKey": "S1yaHC6UW"
          },
          "input": {
            "nodeId": "ByEzHY7MY",
            "pinKey": "ryTeUROHD1b"
          }
        },
        "H1iBBt7ft": {
          "id": "H1iBBt7ft",
          "output": {
            "nodeId": "Sy8SHtmzY",
            "pinKey": "B1x2RV3eZ"
          },
          "input": {
            "nodeId": "SkMeHtQGY",
            "pinKey": "S10qrR6UZ"
          }
        },
        "SkZUHt7MK": {
          "id": "SkZUHt7MK",
          "output": {
            "nodeId": "SypBBK7zY",
            "pinKey": "B1x2RV3eZ"
          },
          "input": {
            "nodeId": "SkMeHtQGY",
            "pinKey": "rygjH06LW"
          }
        },
        "rkq_BFXGK": {
          "id": "rkq_BFXGK",
          "output": {
            "nodeId": "ByEzHY7MY",
            "pinKey": "S13xLCuHvkW"
          },
          "input": {
            "nodeId": "HyUuSK7zF",
            "pinKey": "HkXK-dGob"
          }
        },
        "BkKxIY7GY": {
          "id": "BkKxIY7GY",
          "output": {
            "nodeId": "Hy8wBK7fY",
            "pinKey": "SJyXI0OrD1-"
          },
          "input": {
            "nodeId": "HyQxLKXzt",
            "pinKey": "HJEh_lLGH"
          }
        },
        "Hy0xIYXzK": {
          "id": "Hy0xIYXzK",
          "output": {
            "nodeId": "HyQxLKXzt",
            "pinKey": "By1A_gLfB"
          },
          "input": {
            "nodeId": "ByEzHY7MY",
            "pinKey": "S1yZIA_rDJZ"
          }
        },
        "By20UFmzK": {
          "id": "By20UFmzK",
          "output": {
            "nodeId": "SJ_RUt7fF",
            "pinKey": "B1x2RV3eZ"
          },
          "input": {
            "nodeId": "SkMeHtQGY",
            "pinKey": "rygjH06LW-$1"
          }
        },
        "H1_yPFQMt": {
          "id": "H1_yPFQMt",
          "output": {
            "nodeId": "ryEJwYQfY",
            "pinKey": "B1x2RV3eZ"
          },
          "input": {
            "nodeId": "SkMeHtQGY",
            "pinKey": "rygjH06LW-$2"
          }
        },
        "SkzGPtmMt": {
          "id": "SkzGPtmMt",
          "output": {
            "nodeId": "H1T-DK7MK",
            "pinKey": "B1x2RV3eZ"
          },
          "input": {
            "nodeId": "SkMeHtQGY",
            "pinKey": "rygjH06LW-$3"
          }
        },
        "BJEzPKQfK": {
          "id": "BJEzPKQfK",
          "output": {
            "nodeId": "HkepZPK7MK",
            "pinKey": "B1x2RV3eZ"
          },
          "input": {
            "nodeId": "SkMeHtQGY",
            "pinKey": "rygjH06LW-$4"
          }
        },
        "rJBGDFmzK": {
          "id": "rJBGDFmzK",
          "output": {
            "nodeId": "rk-6WPYmGF",
            "pinKey": "B1x2RV3eZ"
          },
          "input": {
            "nodeId": "SkMeHtQGY",
            "pinKey": "rygjH06LW-$5"
          }
        },
        "BJPMwFQfF": {
          "id": "BJPMwFQfF",
          "output": {
            "nodeId": "BkG6WDtmft",
            "pinKey": "B1x2RV3eZ"
          },
          "input": {
            "nodeId": "SkMeHtQGY",
            "pinKey": "rygjH06LW-$6"
          }
        },
        "By3UDYQzt": {
          "id": "By3UDYQzt",
          "output": {
            "nodeId": "rkPUDK7zY",
            "pinKey": "B1x2RV3eZ"
          },
          "input": {
            "nodeId": "SkMeHtQGY",
            "pinKey": "rygjH06LW-$7"
          }
        },
        "HypIvK7zK": {
          "id": "HypIvK7zK",
          "output": {
            "nodeId": "HJgvLPt7GF",
            "pinKey": "B1x2RV3eZ"
          },
          "input": {
            "nodeId": "SkMeHtQGY",
            "pinKey": "rygjH06LW-$8"
          }
        },
        "HkJwwtmzK": {
          "id": "HkJwwtmzK",
          "output": {
            "nodeId": "ByZDLwKQMY",
            "pinKey": "B1x2RV3eZ"
          },
          "input": {
            "nodeId": "SkMeHtQGY",
            "pinKey": "rygjH06LW-$9"
          }
        },
        "HkbDwY7GK": {
          "id": "HkbDwY7GK",
          "output": {
            "nodeId": "HJGD8vtXfF",
            "pinKey": "B1x2RV3eZ"
          },
          "input": {
            "nodeId": "SkMeHtQGY",
            "pinKey": "rygjH06LW-$10"
          }
        },
        "BJbRPFmft": {
          "id": "BJbRPFmft",
          "output": {
            "nodeId": "S1howtXGt",
            "pinKey": "B1x2RV3eZ"
          },
          "input": {
            "nodeId": "SkMeHtQGY",
            "pinKey": "rygjH06LW-$11"
          }
        },
        "HkQAvKQfF": {
          "id": "HkQAvKQfF",
          "output": {
            "nodeId": "HyeniPFQzt",
            "pinKey": "B1x2RV3eZ"
          },
          "input": {
            "nodeId": "SkMeHtQGY",
            "pinKey": "rygjH06LW-$12"
          }
        },
        "By4RPFXzF": {
          "id": "By4RPFXzF",
          "output": {
            "nodeId": "BJbnsDFXGY",
            "pinKey": "B1x2RV3eZ"
          },
          "input": {
            "nodeId": "SkMeHtQGY",
            "pinKey": "rygjH06LW-$13"
          }
        },
        "HkURPF7fK": {
          "id": "HkURPF7fK",
          "output": {
            "nodeId": "SyG2ovFQGK",
            "pinKey": "B1x2RV3eZ"
          },
          "input": {
            "nodeId": "SkMeHtQGY",
            "pinKey": "rygjH06LW-$14"
          }
        },
        "SyKnoP4fK": {
          "id": "SyKnoP4fK",
          "output": {
            "nodeId": "S1NbRH1fF",
            "pinKey": "Bk4gU0drwJ-"
          },
          "input": {
            "nodeId": "HJhsjPVGY",
            "pinKey": "SkSuD6LMb"
          }
        },
        "By33jP4GK": {
          "id": "By33jP4GK",
          "output": {
            "nodeId": "HJhsjPVGY",
            "pinKey": "Bk4gU0drwJ-"
          },
          "input": {
            "nodeId": "SygsQUyzt",
            "pinKey": "SkSuD6LMb"
          }
        },
        "SJ5aiv4Mt": {
          "id": "SJ5aiv4Mt",
          "output": {
            "nodeId": "SygsQUyzt",
            "pinKey": "Bk4gU0drwJ-"
          },
          "input": {
            "nodeId": "Sk1psv4fF",
            "pinKey": "SkSuD6LMb"
          }
        },
        "H166oPVGY": {
          "id": "H166oPVGY",
          "output": {
            "nodeId": "Sk1psv4fF",
            "pinKey": "Bk4gU0drwJ-"
          },
          "input": {
            "nodeId": "SJSiQ8JzF",
            "pinKey": "SkSuD6LMb"
          }
        },
        "rkt0iP4zt": {
          "id": "rkt0iP4zt",
          "output": {
            "nodeId": "SJSiQ8JzF",
            "pinKey": "Bk4gU0drwJ-"
          },
          "input": {
            "nodeId": "ByZCsP4Gt",
            "pinKey": "SkSuD6LMb"
          }
        },
        "rJ2AjwEGY": {
          "id": "rJ2AjwEGY",
          "output": {
            "nodeId": "ByZCsP4Gt",
            "pinKey": "Bk4gU0drwJ-"
          },
          "input": {
            "nodeId": "Sk_smIkGY",
            "pinKey": "SkSuD6LMb"
          }
        },
        "rkQy3v4fF": {
          "id": "rkQy3v4fF",
          "output": {
            "nodeId": "Sk_smIkGY",
            "pinKey": "Bk4gU0drwJ-"
          },
          "input": {
            "nodeId": "B1kJ3P4MY",
            "pinKey": "SkSuD6LMb"
          }
        },
        "S1iJ3wVGY": {
          "id": "S1iJ3wVGY",
          "output": {
            "nodeId": "B1kJ3P4MY",
            "pinKey": "Bk4gU0drwJ-"
          },
          "input": {
            "nodeId": "ry-yNIJzt",
            "pinKey": "BJI7P8t9Z"
          }
        },
        "HJ8oO54fK": {
          "id": "HJ8oO54fK",
          "output": {
            "nodeId": "S1NbRH1fF",
            "pinKey": "HkU3vNoTW"
          },
          "input": {
            "nodeId": "BJxuD8mMt",
            "pinKey": "SJMVU0urvkZ"
          }
        },
        "Syiju5EMF": {
          "id": "Syiju5EMF",
          "output": {
            "nodeId": "S1NbRH1fF",
            "pinKey": "HkU3vNoTW"
          },
          "input": {
            "nodeId": "r1c_P87ft",
            "pinKey": "SJMVU0urvkZ"
          }
        },
        "BJCoO5Nft": {
          "id": "BJCoO5Nft",
          "output": {
            "nodeId": "S1NbRH1fF",
            "pinKey": "HkU3vNoTW"
          },
          "input": {
            "nodeId": "Bksdv8QGY",
            "pinKey": "SJMVU0urvkZ"
          }
        },
        "Hkb3O54GF": {
          "id": "Hkb3O54GF",
          "output": {
            "nodeId": "S1NbRH1fF",
            "pinKey": "HkU3vNoTW"
          },
          "input": {
            "nodeId": "HJ3dwUXMK",
            "pinKey": "SJMVU0urvkZ"
          }
        },
        "SJZCucNzF": {
          "id": "SJZCucNzF",
          "output": {
            "nodeId": "HkfVZUXMY",
            "pinKey": "BJ--G1tI-"
          },
          "input": {
            "nodeId": "BJxuD8mMt",
            "pinKey": "r1bVLR_BPJW"
          }
        },
        "Bku0uc4ft": {
          "id": "Bku0uc4ft",
          "output": {
            "nodeId": "HkfVZUXMY",
            "pinKey": "BJ--G1tI-"
          },
          "input": {
            "nodeId": "HJKDkwXGY",
            "pinKey": "r1bVLR_BPJW"
          }
        },
        "rkkyFcNfK": {
          "id": "rkkyFcNfK",
          "output": {
            "nodeId": "HkfVZUXMY",
            "pinKey": "BJ--G1tI-"
          },
          "input": {
            "nodeId": "B11dJDXGY",
            "pinKey": "r1bVLR_BPJW"
          }
        },
        "rkQWKcEGF": {
          "id": "rkQWKcEGF",
          "output": {
            "nodeId": "SygsQUyzt",
            "pinKey": "HkU3vNoTW"
          },
          "input": {
            "nodeId": "SyfPyD7ft",
            "pinKey": "SJMVU0urvkZ"
          }
        },
        "ryw-YcNGY": {
          "id": "ryw-YcNGY",
          "output": {
            "nodeId": "SygsQUyzt",
            "pinKey": "HkU3vNoTW"
          },
          "input": {
            "nodeId": "rkezPywQGt",
            "pinKey": "SJMVU0urvkZ"
          }
        },
        "ry9WY9EGF": {
          "id": "ry9WY9EGF",
          "output": {
            "nodeId": "SygsQUyzt",
            "pinKey": "HkU3vNoTW"
          },
          "input": {
            "nodeId": "Hy-MvJw7GF",
            "pinKey": "SJMVU0urvkZ"
          }
        },
        "S10bYcNMY": {
          "id": "S10bYcNMY",
          "output": {
            "nodeId": "SygsQUyzt",
            "pinKey": "HkU3vNoTW"
          },
          "input": {
            "nodeId": "HJGzP1vQGt",
            "pinKey": "SJMVU0urvkZ"
          }
        },
        "BySQY9EzF": {
          "id": "BySQY9EzF",
          "output": {
            "nodeId": "SJSiQ8JzF",
            "pinKey": "HkU3vNoTW"
          },
          "input": {
            "nodeId": "HJKDkwXGY",
            "pinKey": "SJMVU0urvkZ"
          }
        },
        "rkOmYq4GF": {
          "id": "rkOmYq4GF",
          "output": {
            "nodeId": "SJSiQ8JzF",
            "pinKey": "HkU3vNoTW"
          },
          "input": {
            "nodeId": "SJlKPJwQfY",
            "pinKey": "SJMVU0urvkZ"
          }
        },
        "Hy3mF5VGt": {
          "id": "Hy3mF5VGt",
          "output": {
            "nodeId": "SJSiQ8JzF",
            "pinKey": "HkU3vNoTW"
          },
          "input": {
            "nodeId": "HJ-tv1wXGY",
            "pinKey": "SJMVU0urvkZ"
          }
        },
        "S11VFcEGt": {
          "id": "S11VFcEGt",
          "output": {
            "nodeId": "SJSiQ8JzF",
            "pinKey": "HkU3vNoTW"
          },
          "input": {
            "nodeId": "HJfFD1PXGF",
            "pinKey": "SJMVU0urvkZ"
          }
        },
        "Sk7St94zK": {
          "id": "Sk7St94zK",
          "output": {
            "nodeId": "Sk_smIkGY",
            "pinKey": "HkU3vNoTW"
          },
          "input": {
            "nodeId": "B11dJDXGY",
            "pinKey": "SJMVU0urvkZ"
          }
        },
        "HkLHK9NMF": {
          "id": "HkLHK9NMF",
          "output": {
            "nodeId": "Sk_smIkGY",
            "pinKey": "HkU3vNoTW"
          },
          "input": {
            "nodeId": "S1lJOJDmGY",
            "pinKey": "SJMVU0urvkZ"
          }
        },
        "HycHY9NGY": {
          "id": "HycHY9NGY",
          "output": {
            "nodeId": "Sk_smIkGY",
            "pinKey": "HkU3vNoTW"
          },
          "input": {
            "nodeId": "Hkbkd1D7MK",
            "pinKey": "SJMVU0urvkZ"
          }
        },
        "HJaSFcEzt": {
          "id": "HJaSFcEzt",
          "output": {
            "nodeId": "Sk_smIkGY",
            "pinKey": "HkU3vNoTW"
          },
          "input": {
            "nodeId": "BJfJuyvXzK",
            "pinKey": "SJMVU0urvkZ"
          }
        },
        "HJIiFcVzt": {
          "id": "HJIiFcVzt",
          "output": {
            "nodeId": "ryREZLmfK",
            "pinKey": "BJ--G1tI-"
          },
          "input": {
            "nodeId": "r1c_P87ft",
            "pinKey": "r1bVLR_BPJW"
          }
        },
        "ByYsF9VGt": {
          "id": "ByYsF9VGt",
          "output": {
            "nodeId": "ryREZLmfK",
            "pinKey": "BJ--G1tI-"
          },
          "input": {
            "nodeId": "rkezPywQGt",
            "pinKey": "r1bVLR_BPJW"
          }
        },
        "S1hjFc4ft": {
          "id": "S1hjFc4ft",
          "output": {
            "nodeId": "ryREZLmfK",
            "pinKey": "BJ--G1tI-"
          },
          "input": {
            "nodeId": "SJlKPJwQfY",
            "pinKey": "r1bVLR_BPJW"
          }
        },
        "Byz3Y54ft": {
          "id": "Byz3Y54ft",
          "output": {
            "nodeId": "ryREZLmfK",
            "pinKey": "BJ--G1tI-"
          },
          "input": {
            "nodeId": "S1lJOJDmGY",
            "pinKey": "r1bVLR_BPJW"
          }
        },
        "HyApK5EfY": {
          "id": "HyApK5EfY",
          "output": {
            "nodeId": "H1USZU7Mt",
            "pinKey": "BJ--G1tI-"
          },
          "input": {
            "nodeId": "Bksdv8QGY",
            "pinKey": "r1bVLR_BPJW"
          }
        },
        "ryzRYqEGF": {
          "id": "ryzRYqEGF",
          "output": {
            "nodeId": "H1USZU7Mt",
            "pinKey": "BJ--G1tI-"
          },
          "input": {
            "nodeId": "Hy-MvJw7GF",
            "pinKey": "r1bVLR_BPJW"
          }
        },
        "S18AYq4zt": {
          "id": "S18AYq4zt",
          "output": {
            "nodeId": "H1USZU7Mt",
            "pinKey": "BJ--G1tI-"
          },
          "input": {
            "nodeId": "HJ-tv1wXGY",
            "pinKey": "r1bVLR_BPJW"
          }
        },
        "Byt0Y54zt": {
          "id": "Byt0Y54zt",
          "output": {
            "nodeId": "H1USZU7Mt",
            "pinKey": "BJ--G1tI-"
          },
          "input": {
            "nodeId": "Hkbkd1D7MK",
            "pinKey": "r1bVLR_BPJW"
          }
        },
        "Hksxq94GY": {
          "id": "Hksxq94GY",
          "output": {
            "nodeId": "ByprbIQfK",
            "pinKey": "BJ--G1tI-"
          },
          "input": {
            "nodeId": "BJfJuyvXzK",
            "pinKey": "r1bVLR_BPJW"
          }
        },
        "SkCx9qEGt": {
          "id": "SkCx9qEGt",
          "output": {
            "nodeId": "ByprbIQfK",
            "pinKey": "BJ--G1tI-"
          },
          "input": {
            "nodeId": "HJfFD1PXGF",
            "pinKey": "r1bVLR_BPJW"
          }
        },
        "S1bWq54Gt": {
          "id": "S1bWq54Gt",
          "output": {
            "nodeId": "ByprbIQfK",
            "pinKey": "BJ--G1tI-"
          },
          "input": {
            "nodeId": "HJGzP1vQGt",
            "pinKey": "r1bVLR_BPJW"
          }
        },
        "rJIbqcVzt": {
          "id": "rJIbqcVzt",
          "output": {
            "nodeId": "ByprbIQfK",
            "pinKey": "BJ--G1tI-"
          },
          "input": {
            "nodeId": "HJ3dwUXMK",
            "pinKey": "r1bVLR_BPJW"
          }
        },
        "HkHVc54ft": {
          "id": "HkHVc54ft",
          "output": {
            "nodeId": "B11dJDXGY",
            "pinKey": "B1gN80uHvk-"
          },
          "input": {
            "nodeId": "Hy8wBK7fY",
            "pinKey": "BJaG80urD1-"
          }
        },
        "SJKE5cEzY": {
          "id": "SJKE5cEzY",
          "output": {
            "nodeId": "B11dJDXGY",
            "pinKey": "B1gN80uHvk-"
          },
          "input": {
            "nodeId": "SkMeHtQGY",
            "pinKey": "rkmiHCaIZ"
          }
        },
        "SJDS5qEzK": {
          "id": "SJDS5qEzK",
          "output": {
            "nodeId": "S1lJOJDmGY",
            "pinKey": "B1gN80uHvk-"
          },
          "input": {
            "nodeId": "Hy8wBK7fY",
            "pinKey": "HJCfI0dBDkb"
          }
        },
        "r1KB5qVGK": {
          "id": "r1KB5qVGK",
          "output": {
            "nodeId": "S1lJOJDmGY",
            "pinKey": "B1gN80uHvk-"
          },
          "input": {
            "nodeId": "SkMeHtQGY",
            "pinKey": "rJUjrCTUb"
          }
        },
        "BJG85c4fF": {
          "id": "BJG85c4fF",
          "output": {
            "nodeId": "Hkbkd1D7MK",
            "pinKey": "B1gN80uHvk-"
          },
          "input": {
            "nodeId": "Hy8wBK7fY",
            "pinKey": "HJCfI0dBDkb-$1"
          }
        },
        "SJrUqcVGK": {
          "id": "SJrUqcVGK",
          "output": {
            "nodeId": "Hkbkd1D7MK",
            "pinKey": "B1gN80uHvk-"
          },
          "input": {
            "nodeId": "SkMeHtQGY",
            "pinKey": "rJUjrCTUb-$1"
          }
        },
        "S1owc54Mt": {
          "id": "S1owc54Mt",
          "output": {
            "nodeId": "BJfJuyvXzK",
            "pinKey": "B1gN80uHvk-"
          },
          "input": {
            "nodeId": "Hy8wBK7fY",
            "pinKey": "HJCfI0dBDkb-$2"
          }
        },
        "ryRvq9EfK": {
          "id": "ryRvq9EfK",
          "output": {
            "nodeId": "BJfJuyvXzK",
            "pinKey": "B1gN80uHvk-"
          },
          "input": {
            "nodeId": "SkMeHtQGY",
            "pinKey": "rJUjrCTUb-$2"
          }
        },
        "rJ-K5qVMt": {
          "id": "rJ-K5qVMt",
          "output": {
            "nodeId": "HJKDkwXGY",
            "pinKey": "B1gN80uHvk-"
          },
          "input": {
            "nodeId": "Hy8wBK7fY",
            "pinKey": "HJCfI0dBDkb-$3"
          }
        },
        "r1Etq9EMY": {
          "id": "r1Etq9EMY",
          "output": {
            "nodeId": "HJKDkwXGY",
            "pinKey": "B1gN80uHvk-"
          },
          "input": {
            "nodeId": "SkMeHtQGY",
            "pinKey": "rJUjrCTUb-$3"
          }
        },
        "BJWq594MK": {
          "id": "BJWq594MK",
          "output": {
            "nodeId": "SJlKPJwQfY",
            "pinKey": "B1gN80uHvk-"
          },
          "input": {
            "nodeId": "SkMeHtQGY",
            "pinKey": "rJUjrCTUb-$4"
          }
        },
        "Hk4955VGK": {
          "id": "Hk4955VGK",
          "output": {
            "nodeId": "SJlKPJwQfY",
            "pinKey": "B1gN80uHvk-"
          },
          "input": {
            "nodeId": "Hy8wBK7fY",
            "pinKey": "HJCfI0dBDkb-$4"
          }
        },
        "ByWic5EzY": {
          "id": "ByWic5EzY",
          "output": {
            "nodeId": "HJ-tv1wXGY",
            "pinKey": "B1gN80uHvk-"
          },
          "input": {
            "nodeId": "Hy8wBK7fY",
            "pinKey": "HJCfI0dBDkb-$5"
          }
        },
        "BJPi9qVzY": {
          "id": "BJPi9qVzY",
          "output": {
            "nodeId": "HJ-tv1wXGY",
            "pinKey": "B1gN80uHvk-"
          },
          "input": {
            "nodeId": "SkMeHtQGY",
            "pinKey": "rJUjrCTUb-$5"
          }
        },
        "B1Xnq5VMY": {
          "id": "B1Xnq5VMY",
          "output": {
            "nodeId": "HJfFD1PXGF",
            "pinKey": "B1gN80uHvk-"
          },
          "input": {
            "nodeId": "Hy8wBK7fY",
            "pinKey": "HJCfI0dBDkb-$6"
          }
        },
        "B18n954MY": {
          "id": "B18n954MY",
          "output": {
            "nodeId": "HJfFD1PXGF",
            "pinKey": "B1gN80uHvk-"
          },
          "input": {
            "nodeId": "SkMeHtQGY",
            "pinKey": "rJUjrCTUb-$6"
          }
        },
        "SJngjc4Mt": {
          "id": "SJngjc4Mt",
          "output": {
            "nodeId": "SyfPyD7ft",
            "pinKey": "B1gN80uHvk-"
          },
          "input": {
            "nodeId": "SkMeHtQGY",
            "pinKey": "rJUjrCTUb-$7"
          }
        },
        "BJbWs5NfY": {
          "id": "BJbWs5NfY",
          "output": {
            "nodeId": "SyfPyD7ft",
            "pinKey": "B1gN80uHvk-"
          },
          "input": {
            "nodeId": "Hy8wBK7fY",
            "pinKey": "HJCfI0dBDkb-$7"
          }
        },
        "rJOZo9NfK": {
          "id": "rJOZo9NfK",
          "output": {
            "nodeId": "rkezPywQGt",
            "pinKey": "B1gN80uHvk-"
          },
          "input": {
            "nodeId": "Hy8wBK7fY",
            "pinKey": "HJCfI0dBDkb-$8"
          }
        },
        "S1QfjqVMK": {
          "id": "S1QfjqVMK",
          "output": {
            "nodeId": "rkezPywQGt",
            "pinKey": "B1gN80uHvk-"
          },
          "input": {
            "nodeId": "SkMeHtQGY",
            "pinKey": "rJUjrCTUb-$8"
          }
        },
        "Bk5MicNft": {
          "id": "Bk5MicNft",
          "output": {
            "nodeId": "Hy-MvJw7GF",
            "pinKey": "B1gN80uHvk-"
          },
          "input": {
            "nodeId": "Hy8wBK7fY",
            "pinKey": "HJCfI0dBDkb-$9"
          }
        },
        "B1M7oc4MK": {
          "id": "B1M7oc4MK",
          "output": {
            "nodeId": "Hy-MvJw7GF",
            "pinKey": "B1gN80uHvk-"
          },
          "input": {
            "nodeId": "SkMeHtQGY",
            "pinKey": "rJUjrCTUb-$9"
          }
        },
        "r1b4jcEMK": {
          "id": "r1b4jcEMK",
          "output": {
            "nodeId": "HJGzP1vQGt",
            "pinKey": "B1gN80uHvk-"
          },
          "input": {
            "nodeId": "Hy8wBK7fY",
            "pinKey": "HJCfI0dBDkb-$10"
          }
        },
        "rkFNs94MY": {
          "id": "rkFNs94MY",
          "output": {
            "nodeId": "HJGzP1vQGt",
            "pinKey": "B1gN80uHvk-"
          },
          "input": {
            "nodeId": "SkMeHtQGY",
            "pinKey": "rJUjrCTUb-$10"
          }
        },
        "H17HjqNGt": {
          "id": "H17HjqNGt",
          "output": {
            "nodeId": "HJ3dwUXMK",
            "pinKey": "B1gN80uHvk-"
          },
          "input": {
            "nodeId": "Hy8wBK7fY",
            "pinKey": "HJCfI0dBDkb-$14"
          }
        },
        "SJJ8jqVzY": {
          "id": "SJJ8jqVzY",
          "output": {
            "nodeId": "HJ3dwUXMK",
            "pinKey": "B1gN80uHvk-"
          },
          "input": {
            "nodeId": "SkMeHtQGY",
            "pinKey": "rJUjrCTUb-$14"
          }
        },
        "SkGio54MY": {
          "id": "SkGio54MY",
          "output": {
            "nodeId": "BJxuD8mMt",
            "pinKey": "B1gN80uHvk-"
          },
          "input": {
            "nodeId": "SkMeHtQGY",
            "pinKey": "rJUjrCTUb-$11"
          }
        },
        "HkisocEMF": {
          "id": "HkisocEMF",
          "output": {
            "nodeId": "BJxuD8mMt",
            "pinKey": "B1gN80uHvk-"
          },
          "input": {
            "nodeId": "Hy8wBK7fY",
            "pinKey": "HJCfI0dBDkb-$11"
          }
        },
        "S173sq4zK": {
          "id": "S173sq4zK",
          "output": {
            "nodeId": "r1c_P87ft",
            "pinKey": "B1gN80uHvk-"
          },
          "input": {
            "nodeId": "SkMeHtQGY",
            "pinKey": "rJUjrCTUb-$12"
          }
        },
        "HyR3j9VMK": {
          "id": "HyR3j9VMK",
          "output": {
            "nodeId": "r1c_P87ft",
            "pinKey": "B1gN80uHvk-"
          },
          "input": {
            "nodeId": "Hy8wBK7fY",
            "pinKey": "HJCfI0dBDkb-$12"
          }
        },
        "Syr6jc4GF": {
          "id": "Syr6jc4GF",
          "output": {
            "nodeId": "Bksdv8QGY",
            "pinKey": "B1gN80uHvk-"
          },
          "input": {
            "nodeId": "Hy8wBK7fY",
            "pinKey": "HJCfI0dBDkb-$13"
          }
        },
        "Bk66jc4MY": {
          "id": "Bk66jc4MY",
          "output": {
            "nodeId": "Bksdv8QGY",
            "pinKey": "B1gN80uHvk-"
          },
          "input": {
            "nodeId": "SkMeHtQGY",
            "pinKey": "rJUjrCTUb-$13"
          }
        }
      },
      "nodes": {
        "r17aXNjbt": {
          "boundLiterals": {
            "rJjXFA9JQ": "D6",
            "BygApTqym": "Continuously",
            "HJ6HsEngZ": "True"
          },
          "id": "r17aXNjbt",
          "type": "xod/gpio/digital-write",
          "position": {
            "x": 8,
            "y": 3,
            "units": "slots"
          }
        },
        "BkgC14VoZF": {
          "boundLiterals": {
            "rJjXFA9JQ": "D7",
            "HJ6HsEngZ": "True"
          },
          "id": "BkgC14VoZF",
          "type": "xod/gpio/digital-write",
          "position": {
            "x": 8,
            "y": 5,
            "units": "slots"
          }
        },
        "ryxplENiZt": {
          "boundLiterals": {
            "rJjXFA9JQ": "D8",
            "HJ6HsEngZ": "True"
          },
          "id": "ryxplENiZt",
          "type": "xod/gpio/digital-write",
          "position": {
            "x": 8,
            "y": 7,
            "units": "slots"
          }
        },
        "HyM6g44jbY": {
          "boundLiterals": {
            "rJjXFA9JQ": "D9",
            "HJ6HsEngZ": "True"
          },
          "id": "HyM6g44jbY",
          "type": "xod/gpio/digital-write",
          "position": {
            "x": 8,
            "y": 9,
            "units": "slots"
          }
        },
        "S1NbRH1fF": {
          "boundLiterals": {
            "Skre8ROSv1-": "0.05",
            "HkU3vNoTW": "False"
          },
          "id": "S1NbRH1fF",
          "type": "xod/core/delay",
          "position": {
            "x": 4,
            "y": 3,
            "units": "slots"
          }
        },
        "H10Kf81zt": {
          "id": "H10Kf81zt",
          "type": "xod/core/not",
          "position": {
            "x": 7,
            "y": 3,
            "units": "slots"
          }
        },
        "SygsQUyzt": {
          "boundLiterals": {
            "Skre8ROSv1-": "0.05",
            "HkU3vNoTW": "False"
          },
          "id": "SygsQUyzt",
          "type": "xod/core/delay",
          "position": {
            "x": 4,
            "y": 5,
            "units": "slots"
          }
        },
        "H1gejmI1zF": {
          "id": "H1gejmI1zF",
          "type": "xod/core/not",
          "position": {
            "x": 7,
            "y": 5,
            "units": "slots"
          }
        },
        "SJSiQ8JzF": {
          "boundLiterals": {
            "Skre8ROSv1-": "0.05",
            "HkU3vNoTW": "False"
          },
          "id": "SJSiQ8JzF",
          "type": "xod/core/delay",
          "position": {
            "x": 4,
            "y": 7,
            "units": "slots"
          }
        },
        "rylro7L1GK": {
          "id": "rylro7L1GK",
          "type": "xod/core/not",
          "position": {
            "x": 7,
            "y": 7,
            "units": "slots"
          }
        },
        "Sk_smIkGY": {
          "boundLiterals": {
            "Skre8ROSv1-": "0.05",
            "HkU3vNoTW": "False"
          },
          "id": "Sk_smIkGY",
          "type": "xod/core/delay",
          "position": {
            "x": 4,
            "y": 9,
            "units": "slots"
          }
        },
        "SJeuiQ81Gt": {
          "id": "SJeuiQ81Gt",
          "type": "xod/core/not",
          "position": {
            "x": 7,
            "y": 9,
            "units": "slots"
          }
        },
        "ry-yNIJzt": {
          "id": "ry-yNIJzt",
          "type": "xod/core/defer",
          "position": {
            "x": 2,
            "y": 5,
            "units": "slots"
          }
        },
        "BkzxNL1ft": {
          "id": "BkzxNL1ft",
          "type": "xod/core/any",
          "position": {
            "x": 4,
            "y": 2,
            "units": "slots"
          }
        },
        "rkAeEL1Gt": {
          "id": "rkAeEL1Gt",
          "type": "xod/core/boot",
          "position": {
            "x": 5,
            "y": 1,
            "units": "slots"
          }
        },
        "HkfVZUXMY": {
          "boundLiterals": {
            "ByNiWkt8Z": "D2"
          },
          "id": "HkfVZUXMY",
          "type": "xod/common-hardware/button",
          "position": {
            "x": 24,
            "y": 3,
            "units": "slots"
          }
        },
        "ryREZLmfK": {
          "boundLiterals": {
            "ByNiWkt8Z": "D3"
          },
          "id": "ryREZLmfK",
          "type": "xod/common-hardware/button",
          "position": {
            "x": 24,
            "y": 5,
            "units": "slots"
          }
        },
        "H1USZU7Mt": {
          "boundLiterals": {
            "ByNiWkt8Z": "D4"
          },
          "id": "H1USZU7Mt",
          "type": "xod/common-hardware/button",
          "position": {
            "x": 24,
            "y": 7,
            "units": "slots"
          }
        },
        "ByprbIQfK": {
          "boundLiterals": {
            "ByNiWkt8Z": "D5"
          },
          "id": "ByprbIQfK",
          "type": "xod/common-hardware/button",
          "position": {
            "x": 24,
            "y": 9,
            "units": "slots"
          }
        },
        "BJxuD8mMt": {
          "label": "D",
          "id": "BJxuD8mMt",
          "type": "xod/core/and",
          "position": {
            "x": 12,
            "y": 3,
            "units": "slots"
          }
        },
        "r1c_P87ft": {
          "label": "#",
          "id": "r1c_P87ft",
          "type": "xod/core/and",
          "position": {
            "x": 15,
            "y": 3,
            "units": "slots"
          }
        },
        "Bksdv8QGY": {
          "label": "0",
          "id": "Bksdv8QGY",
          "type": "xod/core/and",
          "position": {
            "x": 18,
            "y": 3,
            "units": "slots"
          }
        },
        "HJ3dwUXMK": {
          "label": "*",
          "id": "HJ3dwUXMK",
          "type": "xod/core/and",
          "position": {
            "x": 21,
            "y": 3,
            "units": "slots"
          }
        },
        "SyfPyD7ft": {
          "label": "C",
          "id": "SyfPyD7ft",
          "type": "xod/core/and",
          "position": {
            "x": 12,
            "y": 5,
            "units": "slots"
          }
        },
        "rkezPywQGt": {
          "label": "9",
          "id": "rkezPywQGt",
          "type": "xod/core/and",
          "position": {
            "x": 15,
            "y": 5,
            "units": "slots"
          }
        },
        "Hy-MvJw7GF": {
          "label": "8",
          "id": "Hy-MvJw7GF",
          "type": "xod/core/and",
          "position": {
            "x": 18,
            "y": 5,
            "units": "slots"
          }
        },
        "HJGzP1vQGt": {
          "label": "7",
          "id": "HJGzP1vQGt",
          "type": "xod/core/and",
          "position": {
            "x": 21,
            "y": 5,
            "units": "slots"
          }
        },
        "HJKDkwXGY": {
          "label": "B",
          "id": "HJKDkwXGY",
          "type": "xod/core/and",
          "position": {
            "x": 12,
            "y": 7,
            "units": "slots"
          }
        },
        "SJlKPJwQfY": {
          "label": "6",
          "id": "SJlKPJwQfY",
          "type": "xod/core/and",
          "position": {
            "x": 15,
            "y": 7,
            "units": "slots"
          }
        },
        "HJ-tv1wXGY": {
          "label": "5",
          "id": "HJ-tv1wXGY",
          "type": "xod/core/and",
          "position": {
            "x": 18,
            "y": 7,
            "units": "slots"
          }
        },
        "HJfFD1PXGF": {
          "label": "4",
          "id": "HJfFD1PXGF",
          "type": "xod/core/and",
          "position": {
            "x": 21,
            "y": 7,
            "units": "slots"
          }
        },
        "B11dJDXGY": {
          "label": "A",
          "id": "B11dJDXGY",
          "type": "xod/core/and",
          "position": {
            "x": 12,
            "y": 9,
            "units": "slots"
          }
        },
        "S1lJOJDmGY": {
          "label": "3",
          "id": "S1lJOJDmGY",
          "type": "xod/core/and",
          "position": {
            "x": 15,
            "y": 9,
            "units": "slots"
          }
        },
        "Hkbkd1D7MK": {
          "label": "2",
          "id": "Hkbkd1D7MK",
          "type": "xod/core/and",
          "position": {
            "x": 18,
            "y": 9,
            "units": "slots"
          }
        },
        "BJfJuyvXzK": {
          "label": "1",
          "id": "BJfJuyvXzK",
          "type": "xod/core/and",
          "position": {
            "x": 21,
            "y": 9,
            "units": "slots"
          }
        },
        "SkMeHtQGY": {
          "arityLevel": 15,
          "id": "SkMeHtQGY",
          "type": "xod/core/select",
          "position": {
            "x": 6,
            "y": 14,
            "units": "slots"
          }
        },
        "ByEzHY7MY": {
          "id": "ByEzHY7MY",
          "type": "xod/core/if-else",
          "position": {
            "x": 5,
            "y": 16,
            "units": "slots"
          }
        },
        "B1lXHFQGK": {
          "boundLiterals": {
            "B1x2RV3eZ": "\"@\""
          },
          "id": "B1lXHFQGK",
          "type": "xod/core/constant-string",
          "position": {
            "x": 7,
            "y": 15,
            "units": "slots"
          }
        },
        "Sy8SHtmzY": {
          "boundLiterals": {
            "B1x2RV3eZ": "\"A\""
          },
          "id": "Sy8SHtmzY",
          "type": "xod/core/constant-string",
          "position": {
            "x": 6,
            "y": 13,
            "units": "slots"
          }
        },
        "SypBBK7zY": {
          "boundLiterals": {
            "B1x2RV3eZ": "\"3\""
          },
          "id": "SypBBK7zY",
          "type": "xod/core/constant-string",
          "position": {
            "x": 8,
            "y": 13,
            "units": "slots"
          }
        },
        "Hy8wBK7fY": {
          "arityLevel": 15,
          "id": "Hy8wBK7fY",
          "type": "xod/core/or",
          "position": {
            "x": 9,
            "y": 12,
            "units": "slots"
          }
        },
        "HyUuSK7zF": {
          "id": "HyUuSK7zF",
          "type": "xod/debug/watch",
          "position": {
            "x": 5,
            "y": 17,
            "units": "slots"
          }
        },
        "HyQxLKXzt": {
          "boundLiterals": {
            "Sk3hdlIMr": "0.5"
          },
          "id": "HyQxLKXzt",
          "type": "xod/core/overrun",
          "position": {
            "x": 3,
            "y": 13,
            "units": "slots"
          }
        },
        "SJ_RUt7fF": {
          "boundLiterals": {
            "B1x2RV3eZ": "\"2\""
          },
          "id": "SJ_RUt7fF",
          "type": "xod/core/constant-string",
          "position": {
            "x": 10,
            "y": 13,
            "units": "slots"
          }
        },
        "ryEJwYQfY": {
          "boundLiterals": {
            "B1x2RV3eZ": "\"1\""
          },
          "id": "ryEJwYQfY",
          "type": "xod/core/constant-string",
          "position": {
            "x": 12,
            "y": 13,
            "units": "slots"
          }
        },
        "H1T-DK7MK": {
          "boundLiterals": {
            "B1x2RV3eZ": "\"B\""
          },
          "id": "H1T-DK7MK",
          "type": "xod/core/constant-string",
          "position": {
            "x": 14,
            "y": 13,
            "units": "slots"
          }
        },
        "HkepZPK7MK": {
          "boundLiterals": {
            "B1x2RV3eZ": "\"6\""
          },
          "id": "HkepZPK7MK",
          "type": "xod/core/constant-string",
          "position": {
            "x": 16,
            "y": 13,
            "units": "slots"
          }
        },
        "rk-6WPYmGF": {
          "boundLiterals": {
            "B1x2RV3eZ": "\"5\""
          },
          "id": "rk-6WPYmGF",
          "type": "xod/core/constant-string",
          "position": {
            "x": 18,
            "y": 13,
            "units": "slots"
          }
        },
        "BkG6WDtmft": {
          "boundLiterals": {
            "B1x2RV3eZ": "\"4\""
          },
          "id": "BkG6WDtmft",
          "type": "xod/core/constant-string",
          "position": {
            "x": 20,
            "y": 13,
            "units": "slots"
          }
        },
        "rkPUDK7zY": {
          "boundLiterals": {
            "B1x2RV3eZ": "\"C\""
          },
          "id": "rkPUDK7zY",
          "type": "xod/core/constant-string",
          "position": {
            "x": 22,
            "y": 13,
            "units": "slots"
          }
        },
        "HJgvLPt7GF": {
          "boundLiterals": {
            "B1x2RV3eZ": "\"9\""
          },
          "id": "HJgvLPt7GF",
          "type": "xod/core/constant-string",
          "position": {
            "x": 24,
            "y": 13,
            "units": "slots"
          }
        },
        "ByZDLwKQMY": {
          "boundLiterals": {
            "B1x2RV3eZ": "\"8\""
          },
          "id": "ByZDLwKQMY",
          "type": "xod/core/constant-string",
          "position": {
            "x": 26,
            "y": 13,
            "units": "slots"
          }
        },
        "HJGD8vtXfF": {
          "boundLiterals": {
            "B1x2RV3eZ": "\"7\""
          },
          "id": "HJGD8vtXfF",
          "type": "xod/core/constant-string",
          "position": {
            "x": 28,
            "y": 13,
            "units": "slots"
          }
        },
        "S1howtXGt": {
          "boundLiterals": {
            "B1x2RV3eZ": "\"D\""
          },
          "id": "S1howtXGt",
          "type": "xod/core/constant-string",
          "position": {
            "x": 30,
            "y": 13,
            "units": "slots"
          }
        },
        "HyeniPFQzt": {
          "boundLiterals": {
            "B1x2RV3eZ": "\"#\""
          },
          "id": "HyeniPFQzt",
          "type": "xod/core/constant-string",
          "position": {
            "x": 32,
            "y": 13,
            "units": "slots"
          }
        },
        "BJbnsDFXGY": {
          "boundLiterals": {
            "B1x2RV3eZ": "\"0\""
          },
          "id": "BJbnsDFXGY",
          "type": "xod/core/constant-string",
          "position": {
            "x": 34,
            "y": 13,
            "units": "slots"
          }
        },
        "SyG2ovFQGK": {
          "boundLiterals": {
            "B1x2RV3eZ": "\"*\""
          },
          "id": "SyG2ovFQGK",
          "type": "xod/core/constant-string",
          "position": {
            "x": 36,
            "y": 13,
            "units": "slots"
          }
        },
        "HJhsjPVGY": {
          "boundLiterals": {
            "Skre8ROSv1-": "0.05",
            "HkU3vNoTW": "False"
          },
          "id": "HJhsjPVGY",
          "type": "xod/core/delay",
          "position": {
            "x": 6,
            "y": 4,
            "units": "slots"
          }
        },
        "Sk1psv4fF": {
          "boundLiterals": {
            "Skre8ROSv1-": "0.05",
            "HkU3vNoTW": "False"
          },
          "id": "Sk1psv4fF",
          "type": "xod/core/delay",
          "position": {
            "x": 6,
            "y": 6,
            "units": "slots"
          }
        },
        "ByZCsP4Gt": {
          "boundLiterals": {
            "Skre8ROSv1-": "0.05",
            "HkU3vNoTW": "False"
          },
          "id": "ByZCsP4Gt",
          "type": "xod/core/delay",
          "position": {
            "x": 6,
            "y": 8,
            "units": "slots"
          }
        },
        "B1kJ3P4MY": {
          "boundLiterals": {
            "Skre8ROSv1-": "0.05",
            "HkU3vNoTW": "False"
          },
          "id": "B1kJ3P4MY",
          "type": "xod/core/delay",
          "position": {
            "x": 6,
            "y": 10,
            "units": "slots"
          }
        }
      },
      "path": "@/main"
    },
    "@/keyboard4x4": {
      "links": {
        "SkhMDsYoEGY": {
          "id": "SkhMDsYoEGY",
          "output": {
            "nodeId": "r1VvjtiNzF",
            "pinKey": "r1if8ROSDJ-"
          },
          "input": {
            "nodeId": "HJDoFo4zK",
            "pinKey": "HJ6HsEngZ"
          }
        },
        "SJ6MDotsNfY": {
          "id": "SJ6MDotsNfY",
          "output": {
            "nodeId": "HJ7wsYiVzt",
            "pinKey": "HkU3vNoTW"
          },
          "input": {
            "nodeId": "r1VvjtiNzF",
            "pinKey": "ry3zLA_Bv1Z"
          }
        },
        "By0fvoFoVGY": {
          "id": "By0fvoFoVGY",
          "output": {
            "nodeId": "BkrvsYiVft",
            "pinKey": "HkU3vNoTW"
          },
          "input": {
            "nodeId": "BkIDjYsNzY",
            "pinKey": "ry3zLA_Bv1Z"
          }
        },
        "BkkXvsKsNGY": {
          "id": "BkkXvsKsNGY",
          "output": {
            "nodeId": "S1PvoKiNMt",
            "pinKey": "HkU3vNoTW"
          },
          "input": {
            "nodeId": "HJdPoYoNGK",
            "pinKey": "ry3zLA_Bv1Z"
          }
        },
        "BygXDiFi4fK": {
          "id": "BygXDiFi4fK",
          "output": {
            "nodeId": "SJFDiYiNGF",
            "pinKey": "HkU3vNoTW"
          },
          "input": {
            "nodeId": "rycDoYo4Gt",
            "pinKey": "ry3zLA_Bv1Z"
          }
        },
        "B1bQPoFsNfF": {
          "id": "B1bQPoFsNfF",
          "output": {
            "nodeId": "BkIDjYsNzY",
            "pinKey": "r1if8ROSDJ-"
          },
          "input": {
            "nodeId": "SkgDoFo4Gt",
            "pinKey": "HJ6HsEngZ"
          }
        },
        "BJGXPsYs4MK": {
          "id": "BJGXPsYs4MK",
          "output": {
            "nodeId": "HJdPoYoNGK",
            "pinKey": "r1if8ROSDJ-"
          },
          "input": {
            "nodeId": "BJWviKsNMK",
            "pinKey": "HJ6HsEngZ"
          }
        },
        "BJ7XPiYsEzK": {
          "id": "BJ7XPiYsEzK",
          "output": {
            "nodeId": "rycDoYo4Gt",
            "pinKey": "r1if8ROSDJ-"
          },
          "input": {
            "nodeId": "BJGDsKiEfF",
            "pinKey": "HJ6HsEngZ"
          }
        },
        "HkEQwsFjEMt": {
          "id": "HkEQwsFjEMt",
          "output": {
            "nodeId": "Hk3PsFoVMF",
            "pinKey": "ByHmL0uHPk-"
          },
          "input": {
            "nodeId": "HJ7wsYiVzt",
            "pinKey": "SkSuD6LMb"
          }
        },
        "ByrXwjKoNft": {
          "id": "ByrXwjKoNft",
          "output": {
            "nodeId": "SJoDotsEGK",
            "pinKey": "HJhXDIY9-"
          },
          "input": {
            "nodeId": "Hk3PsFoVMF",
            "pinKey": "ryv7IRdSP1b"
          }
        },
        "SyUXDotjNGF": {
          "id": "SyUXDotjNGF",
          "output": {
            "nodeId": "SyTPoFj4MF",
            "pinKey": "ryVmUAOrvkb"
          },
          "input": {
            "nodeId": "Hk3PsFoVMF",
            "pinKey": "ByU7LRuSPkW"
          }
        },
        "rJDmPjts4MF": {
          "id": "rJDmPjts4MF",
          "output": {
            "nodeId": "B14-PjFo4GK",
            "pinKey": "B1x2RV3eZ"
          },
          "input": {
            "nodeId": "S1mbPsto4MF",
            "pinKey": "r1AgIROHDJW"
          }
        },
        "S1_QwjYj4GF": {
          "id": "S1_QwjYj4GF",
          "output": {
            "nodeId": "H1z-wstiNzK",
            "pinKey": "S1yaHC6UW"
          },
          "input": {
            "nodeId": "S1mbPsto4MF",
            "pinKey": "ryTeUROHD1b"
          }
        },
        "HJYXPstjVMK": {
          "id": "HJYXPstjVMK",
          "output": {
            "nodeId": "ryBWDsYiNGF",
            "pinKey": "B1x2RV3eZ"
          },
          "input": {
            "nodeId": "H1z-wstiNzK",
            "pinKey": "S10qrR6UZ"
          }
        },
        "rk5QDsYjEMY": {
          "id": "rk5QDsYjEMY",
          "output": {
            "nodeId": "BkUZvstiVfK",
            "pinKey": "B1x2RV3eZ"
          },
          "input": {
            "nodeId": "H1z-wstiNzK",
            "pinKey": "rygjH06LW"
          }
        },
        "Bk3XPotsNft": {
          "id": "Bk3XPotsNft",
          "output": {
            "nodeId": "HJDbPits4zt",
            "pinKey": "SJyXI0OrD1-"
          },
          "input": {
            "nodeId": "rytZvitoNzt",
            "pinKey": "HJEh_lLGH"
          }
        },
        "B1pQDsKiNGF": {
          "id": "B1pQDsKiNGF",
          "output": {
            "nodeId": "rytZvitoNzt",
            "pinKey": "By1A_gLfB"
          },
          "input": {
            "nodeId": "S1mbPsto4MF",
            "pinKey": "S1yZIA_rDJZ"
          }
        },
        "ByCQwstj4zK": {
          "id": "ByCQwstj4zK",
          "output": {
            "nodeId": "Sk9WDoKiEzK",
            "pinKey": "B1x2RV3eZ"
          },
          "input": {
            "nodeId": "H1z-wstiNzK",
            "pinKey": "rygjH06LW-$1"
          }
        },
        "HkkEwotj4fK": {
          "id": "HkkEwotj4fK",
          "output": {
            "nodeId": "rkobDoFsNft",
            "pinKey": "B1x2RV3eZ"
          },
          "input": {
            "nodeId": "H1z-wstiNzK",
            "pinKey": "rygjH06LW-$2"
          }
        },
        "HkgEDiti4zK": {
          "id": "HkgEDiti4zK",
          "output": {
            "nodeId": "Bk3ZPits4GY",
            "pinKey": "B1x2RV3eZ"
          },
          "input": {
            "nodeId": "H1z-wstiNzK",
            "pinKey": "rygjH06LW-$3"
          }
        },
        "SJ-NPitoNzF": {
          "id": "SJ-NPitoNzF",
          "output": {
            "nodeId": "S1a-woFs4GY",
            "pinKey": "B1x2RV3eZ"
          },
          "input": {
            "nodeId": "H1z-wstiNzK",
            "pinKey": "rygjH06LW-$4"
          }
        },
        "SJzNDjFjEzK": {
          "id": "SJzNDjFjEzK",
          "output": {
            "nodeId": "SyRbvitsNGY",
            "pinKey": "B1x2RV3eZ"
          },
          "input": {
            "nodeId": "H1z-wstiNzK",
            "pinKey": "rygjH06LW-$5"
          }
        },
        "Sy7VDoKiVGK": {
          "id": "Sy7VDoKiVGK",
          "output": {
            "nodeId": "rJJzwjYoVMK",
            "pinKey": "B1x2RV3eZ"
          },
          "input": {
            "nodeId": "H1z-wstiNzK",
            "pinKey": "rygjH06LW-$6"
          }
        },
        "HkE4PsYo4Mt": {
          "id": "HkE4PsYo4Mt",
          "output": {
            "nodeId": "BklGwsYoVfF",
            "pinKey": "B1x2RV3eZ"
          },
          "input": {
            "nodeId": "H1z-wstiNzK",
            "pinKey": "rygjH06LW-$7"
          }
        },
        "rkHEPjYj4fK": {
          "id": "rkHEPjYj4fK",
          "output": {
            "nodeId": "ByZzwsYjEMK",
            "pinKey": "B1x2RV3eZ"
          },
          "input": {
            "nodeId": "H1z-wstiNzK",
            "pinKey": "rygjH06LW-$8"
          }
        },
        "r1UNwoYiEfY": {
          "id": "r1UNwoYiEfY",
          "output": {
            "nodeId": "H1fzviFi4zY",
            "pinKey": "B1x2RV3eZ"
          },
          "input": {
            "nodeId": "H1z-wstiNzK",
            "pinKey": "rygjH06LW-$9"
          }
        },
        "HJwVPstsEGt": {
          "id": "HJwVPstsEGt",
          "output": {
            "nodeId": "H1XGDiFoVGY",
            "pinKey": "B1x2RV3eZ"
          },
          "input": {
            "nodeId": "H1z-wstiNzK",
            "pinKey": "rygjH06LW-$10"
          }
        },
        "HJdEvsFsVzF": {
          "id": "HJdEvsFsVzF",
          "output": {
            "nodeId": "S1VfwjtjNzY",
            "pinKey": "B1x2RV3eZ"
          },
          "input": {
            "nodeId": "H1z-wstiNzK",
            "pinKey": "rygjH06LW-$11"
          }
        },
        "ByK4DjYiEft": {
          "id": "ByK4DjYiEft",
          "output": {
            "nodeId": "rJSzwiFsVfY",
            "pinKey": "B1x2RV3eZ"
          },
          "input": {
            "nodeId": "H1z-wstiNzK",
            "pinKey": "rygjH06LW-$12"
          }
        },
        "Hk9VDsKiNft": {
          "id": "Hk9VDsKiNft",
          "output": {
            "nodeId": "S1UfDsYoNGF",
            "pinKey": "B1x2RV3eZ"
          },
          "input": {
            "nodeId": "H1z-wstiNzK",
            "pinKey": "rygjH06LW-$13"
          }
        },
        "BJsVvstjEzK": {
          "id": "BJsVvstjEzK",
          "output": {
            "nodeId": "H1PzviKsVMF",
            "pinKey": "B1x2RV3eZ"
          },
          "input": {
            "nodeId": "H1z-wstiNzK",
            "pinKey": "rygjH06LW-$14"
          }
        },
        "Sy3VvsKsEGt": {
          "id": "Sy3VvsKsEGt",
          "output": {
            "nodeId": "HJ7wsYiVzt",
            "pinKey": "Bk4gU0drwJ-"
          },
          "input": {
            "nodeId": "H1_zvjto4zY",
            "pinKey": "SkSuD6LMb"
          }
        },
        "SJTVwsKoEzF": {
          "id": "SJTVwsKoEzF",
          "output": {
            "nodeId": "H1_zvjto4zY",
            "pinKey": "Bk4gU0drwJ-"
          },
          "input": {
            "nodeId": "BkrvsYiVft",
            "pinKey": "SkSuD6LMb"
          }
        },
        "rJAVPsFo4fF": {
          "id": "rJAVPsFo4fF",
          "output": {
            "nodeId": "BkrvsYiVft",
            "pinKey": "Bk4gU0drwJ-"
          },
          "input": {
            "nodeId": "ryKfvsts4GK",
            "pinKey": "SkSuD6LMb"
          }
        },
        "r1krDoFoNMY": {
          "id": "r1krDoFoNMY",
          "output": {
            "nodeId": "ryKfvsts4GK",
            "pinKey": "Bk4gU0drwJ-"
          },
          "input": {
            "nodeId": "S1PvoKiNMt",
            "pinKey": "SkSuD6LMb"
          }
        },
        "ryxrvoYiNGF": {
          "id": "ryxrvoYiNGF",
          "output": {
            "nodeId": "S1PvoKiNMt",
            "pinKey": "Bk4gU0drwJ-"
          },
          "input": {
            "nodeId": "S19MPjtsEGK",
            "pinKey": "SkSuD6LMb"
          }
        },
        "rybHDiKjNfY": {
          "id": "rybHDiKjNfY",
          "output": {
            "nodeId": "S19MPjtsEGK",
            "pinKey": "Bk4gU0drwJ-"
          },
          "input": {
            "nodeId": "SJFDiYiNGF",
            "pinKey": "SkSuD6LMb"
          }
        },
        "B1zrDitsNzF": {
          "id": "B1zrDitsNzF",
          "output": {
            "nodeId": "SJFDiYiNGF",
            "pinKey": "Bk4gU0drwJ-"
          },
          "input": {
            "nodeId": "SyiGPjYoEGK",
            "pinKey": "SkSuD6LMb"
          }
        },
        "HkQHDiKs4GK": {
          "id": "HkQHDiKs4GK",
          "output": {
            "nodeId": "SyiGPjYoEGK",
            "pinKey": "Bk4gU0drwJ-"
          },
          "input": {
            "nodeId": "SJoDotsEGK",
            "pinKey": "BJI7P8t9Z"
          }
        },
        "B1VSvoKoNGK": {
          "id": "B1VSvoKoNGK",
          "output": {
            "nodeId": "HJ7wsYiVzt",
            "pinKey": "HkU3vNoTW"
          },
          "input": {
            "nodeId": "HJzewoFiNMK",
            "pinKey": "SJMVU0urvkZ"
          }
        },
        "rkSrwsKjNzY": {
          "id": "rkSrwsKjNzY",
          "output": {
            "nodeId": "HJ7wsYiVzt",
            "pinKey": "HkU3vNoTW"
          },
          "input": {
            "nodeId": "BkQgvitjEMK",
            "pinKey": "SJMVU0urvkZ"
          }
        },
        "S1IBPsFoEMK": {
          "id": "S1IBPsFoEMK",
          "output": {
            "nodeId": "HJ7wsYiVzt",
            "pinKey": "HkU3vNoTW"
          },
          "input": {
            "nodeId": "HJNewsFsEzY",
            "pinKey": "SJMVU0urvkZ"
          }
        },
        "HkDSDoFiVMK": {
          "id": "HkDSDoFiVMK",
          "output": {
            "nodeId": "HJ7wsYiVzt",
            "pinKey": "HkU3vNoTW"
          },
          "input": {
            "nodeId": "BkSeviYiNft",
            "pinKey": "SJMVU0urvkZ"
          }
        },
        "Sk_SwiYs4ft": {
          "id": "Sk_SwiYs4ft",
          "output": {
            "nodeId": "HkCPjFsEMK",
            "pinKey": "BJ--G1tI-"
          },
          "input": {
            "nodeId": "HJzewoFiNMK",
            "pinKey": "r1bVLR_BPJW"
          }
        },
        "BJKHvitsNzY": {
          "id": "BJKHvitsNzY",
          "output": {
            "nodeId": "HkCPjFsEMK",
            "pinKey": "BJ--G1tI-"
          },
          "input": {
            "nodeId": "HJqxDsKs4fF",
            "pinKey": "r1bVLR_BPJW"
          }
        },
        "Sy5rwiFjEGK": {
          "id": "Sy5rwiFjEGK",
          "output": {
            "nodeId": "HkCPjFsEMK",
            "pinKey": "BJ--G1tI-"
          },
          "input": {
            "nodeId": "rJRePsFsNfY",
            "pinKey": "r1bVLR_BPJW"
          }
        },
        "rJsSDoKi4zF": {
          "id": "rJsSDoKi4zF",
          "output": {
            "nodeId": "BkrvsYiVft",
            "pinKey": "HkU3vNoTW"
          },
          "input": {
            "nodeId": "r18gwjtsNGt",
            "pinKey": "SJMVU0urvkZ"
          }
        },
        "BJhHDjYi4fF": {
          "id": "BJhHDjYi4fF",
          "output": {
            "nodeId": "BkrvsYiVft",
            "pinKey": "HkU3vNoTW"
          },
          "input": {
            "nodeId": "Skvlwots4GK",
            "pinKey": "SJMVU0urvkZ"
          }
        },
        "SkTrwjYjVzY": {
          "id": "SkTrwjYjVzY",
          "output": {
            "nodeId": "BkrvsYiVft",
            "pinKey": "HkU3vNoTW"
          },
          "input": {
            "nodeId": "HkdlviFjEfF",
            "pinKey": "SJMVU0urvkZ"
          }
        },
        "HyASPjtoEft": {
          "id": "HyASPjtoEft",
          "output": {
            "nodeId": "BkrvsYiVft",
            "pinKey": "HkU3vNoTW"
          },
          "input": {
            "nodeId": "HJYgDoKjNzY",
            "pinKey": "SJMVU0urvkZ"
          }
        },
        "rkkUDsFjNzF": {
          "id": "rkkUDsFjNzF",
          "output": {
            "nodeId": "S1PvoKiNMt",
            "pinKey": "HkU3vNoTW"
          },
          "input": {
            "nodeId": "HJqxDsKs4fF",
            "pinKey": "SJMVU0urvkZ"
          }
        },
        "HkeIwitiEft": {
          "id": "HkeIwitiEft",
          "output": {
            "nodeId": "S1PvoKiNMt",
            "pinKey": "HkU3vNoTW"
          },
          "input": {
            "nodeId": "ByjxPjtoVMt",
            "pinKey": "SJMVU0urvkZ"
          }
        },
        "S1ZIDsYo4GF": {
          "id": "S1ZIDsYo4GF",
          "output": {
            "nodeId": "S1PvoKiNMt",
            "pinKey": "HkU3vNoTW"
          },
          "input": {
            "nodeId": "BJhgwoFo4Gt",
            "pinKey": "SJMVU0urvkZ"
          }
        },
        "HkM8vjYjVGF": {
          "id": "HkM8vjYjVGF",
          "output": {
            "nodeId": "S1PvoKiNMt",
            "pinKey": "HkU3vNoTW"
          },
          "input": {
            "nodeId": "Sk6ewitsNfK",
            "pinKey": "SJMVU0urvkZ"
          }
        },
        "Bk7UDsYsNGK": {
          "id": "Bk7UDsYsNGK",
          "output": {
            "nodeId": "SJFDiYiNGF",
            "pinKey": "HkU3vNoTW"
          },
          "input": {
            "nodeId": "rJRePsFsNfY",
            "pinKey": "SJMVU0urvkZ"
          }
        },
        "HJ4IDsKiVGK": {
          "id": "HJ4IDsKiVGK",
          "output": {
            "nodeId": "SJFDiYiNGF",
            "pinKey": "HkU3vNoTW"
          },
          "input": {
            "nodeId": "BJ1ZPotsVfK",
            "pinKey": "SJMVU0urvkZ"
          }
        },
        "H1B8DjKsEGY": {
          "id": "H1B8DjKsEGY",
          "output": {
            "nodeId": "SJFDiYiNGF",
            "pinKey": "HkU3vNoTW"
          },
          "input": {
            "nodeId": "r1l-DjFoNGF",
            "pinKey": "SJMVU0urvkZ"
          }
        },
        "rkIIwito4fF": {
          "id": "rkIIwito4fF",
          "output": {
            "nodeId": "SJFDiYiNGF",
            "pinKey": "HkU3vNoTW"
          },
          "input": {
            "nodeId": "B1--PjKiVGY",
            "pinKey": "SJMVU0urvkZ"
          }
        },
        "rJw8PiKoEzt": {
          "id": "rJw8PiKoEzt",
          "output": {
            "nodeId": "SkJgDsKi4fF",
            "pinKey": "BJ--G1tI-"
          },
          "input": {
            "nodeId": "BkQgvitjEMK",
            "pinKey": "r1bVLR_BPJW"
          }
        },
        "S1OLDoYi4MY": {
          "id": "S1OLDoYi4MY",
          "output": {
            "nodeId": "SkJgDsKi4fF",
            "pinKey": "BJ--G1tI-"
          },
          "input": {
            "nodeId": "Skvlwots4GK",
            "pinKey": "r1bVLR_BPJW"
          }
        },
        "r1Y8PitsEMt": {
          "id": "r1Y8PitsEMt",
          "output": {
            "nodeId": "SkJgDsKi4fF",
            "pinKey": "BJ--G1tI-"
          },
          "input": {
            "nodeId": "ByjxPjtoVMt",
            "pinKey": "r1bVLR_BPJW"
          }
        },
        "rk58voYjEft": {
          "id": "rk58voYjEft",
          "output": {
            "nodeId": "SkJgDsKi4fF",
            "pinKey": "BJ--G1tI-"
          },
          "input": {
            "nodeId": "BJ1ZPotsVfK",
            "pinKey": "r1bVLR_BPJW"
          }
        },
        "BJoLPiFoNMK": {
          "id": "BJoLPiFoNMK",
          "output": {
            "nodeId": "HygevjtjEzY",
            "pinKey": "BJ--G1tI-"
          },
          "input": {
            "nodeId": "HJNewsFsEzY",
            "pinKey": "r1bVLR_BPJW"
          }
        },
        "Sy38DoFiEfF": {
          "id": "Sy38DoFiEfF",
          "output": {
            "nodeId": "HygevjtjEzY",
            "pinKey": "BJ--G1tI-"
          },
          "input": {
            "nodeId": "HkdlviFjEfF",
            "pinKey": "r1bVLR_BPJW"
          }
        },
        "BypIvsKo4GK": {
          "id": "BypIvsKo4GK",
          "output": {
            "nodeId": "HygevjtjEzY",
            "pinKey": "BJ--G1tI-"
          },
          "input": {
            "nodeId": "BJhgwoFo4Gt",
            "pinKey": "r1bVLR_BPJW"
          }
        },
        "SJAIwjYsEMF": {
          "id": "SJAIwjYsEMF",
          "output": {
            "nodeId": "HygevjtjEzY",
            "pinKey": "BJ--G1tI-"
          },
          "input": {
            "nodeId": "r1l-DjFoNGF",
            "pinKey": "r1bVLR_BPJW"
          }
        },
        "HykwPiYoVzF": {
          "id": "HykwPiYoVzF",
          "output": {
            "nodeId": "SkZgDsYoEMt",
            "pinKey": "BJ--G1tI-"
          },
          "input": {
            "nodeId": "B1--PjKiVGY",
            "pinKey": "r1bVLR_BPJW"
          }
        },
        "SJePDoFjEfK": {
          "id": "SJePDoFjEfK",
          "output": {
            "nodeId": "SkZgDsYoEMt",
            "pinKey": "BJ--G1tI-"
          },
          "input": {
            "nodeId": "Sk6ewitsNfK",
            "pinKey": "r1bVLR_BPJW"
          }
        },
        "B1ZDPjKsNMF": {
          "id": "B1ZDPjKsNMF",
          "output": {
            "nodeId": "SkZgDsYoEMt",
            "pinKey": "BJ--G1tI-"
          },
          "input": {
            "nodeId": "HJYgDoKjNzY",
            "pinKey": "r1bVLR_BPJW"
          }
        },
        "HyfPPstjNMt": {
          "id": "HyfPPstjNMt",
          "output": {
            "nodeId": "SkZgDsYoEMt",
            "pinKey": "BJ--G1tI-"
          },
          "input": {
            "nodeId": "BkSeviYiNft",
            "pinKey": "r1bVLR_BPJW"
          }
        },
        "By7vPjKsEMY": {
          "id": "By7vPjKsEMY",
          "output": {
            "nodeId": "rJRePsFsNfY",
            "pinKey": "B1gN80uHvk-"
          },
          "input": {
            "nodeId": "HJDbPits4zt",
            "pinKey": "BJaG80urD1-"
          }
        },
        "HJNwviFiNGF": {
          "id": "HJNwviFiNGF",
          "output": {
            "nodeId": "rJRePsFsNfY",
            "pinKey": "B1gN80uHvk-"
          },
          "input": {
            "nodeId": "H1z-wstiNzK",
            "pinKey": "rkmiHCaIZ"
          }
        },
        "BkrDviYiVGF": {
          "id": "BkrDviYiVGF",
          "output": {
            "nodeId": "BJ1ZPotsVfK",
            "pinKey": "B1gN80uHvk-"
          },
          "input": {
            "nodeId": "HJDbPits4zt",
            "pinKey": "HJCfI0dBDkb"
          }
        },
        "B1LDwsYi4zK": {
          "id": "B1LDwsYi4zK",
          "output": {
            "nodeId": "BJ1ZPotsVfK",
            "pinKey": "B1gN80uHvk-"
          },
          "input": {
            "nodeId": "H1z-wstiNzK",
            "pinKey": "rJUjrCTUb"
          }
        },
        "rJwwDjYj4zF": {
          "id": "rJwwDjYj4zF",
          "output": {
            "nodeId": "r1l-DjFoNGF",
            "pinKey": "B1gN80uHvk-"
          },
          "input": {
            "nodeId": "HJDbPits4zt",
            "pinKey": "HJCfI0dBDkb-$1"
          }
        },
        "ByuvvjFsVGK": {
          "id": "ByuvvjFsVGK",
          "output": {
            "nodeId": "r1l-DjFoNGF",
            "pinKey": "B1gN80uHvk-"
          },
          "input": {
            "nodeId": "H1z-wstiNzK",
            "pinKey": "rJUjrCTUb-$1"
          }
        },
        "SytvPoFoVzK": {
          "id": "SytvPoFoVzK",
          "output": {
            "nodeId": "B1--PjKiVGY",
            "pinKey": "B1gN80uHvk-"
          },
          "input": {
            "nodeId": "HJDbPits4zt",
            "pinKey": "HJCfI0dBDkb-$2"
          }
        },
        "r1cPvoKjVGK": {
          "id": "r1cPvoKjVGK",
          "output": {
            "nodeId": "B1--PjKiVGY",
            "pinKey": "B1gN80uHvk-"
          },
          "input": {
            "nodeId": "H1z-wstiNzK",
            "pinKey": "rJUjrCTUb-$2"
          }
        },
        "rysDDitjNzK": {
          "id": "rysDDitjNzK",
          "output": {
            "nodeId": "HJqxDsKs4fF",
            "pinKey": "B1gN80uHvk-"
          },
          "input": {
            "nodeId": "HJDbPits4zt",
            "pinKey": "HJCfI0dBDkb-$3"
          }
        },
        "rJhwDsFiVzF": {
          "id": "rJhwDsFiVzF",
          "output": {
            "nodeId": "HJqxDsKs4fF",
            "pinKey": "B1gN80uHvk-"
          },
          "input": {
            "nodeId": "H1z-wstiNzK",
            "pinKey": "rJUjrCTUb-$3"
          }
        },
        "r1pvwsFsNfF": {
          "id": "r1pvwsFsNfF",
          "output": {
            "nodeId": "ByjxPjtoVMt",
            "pinKey": "B1gN80uHvk-"
          },
          "input": {
            "nodeId": "H1z-wstiNzK",
            "pinKey": "rJUjrCTUb-$4"
          }
        },
        "B1RPviYi4GF": {
          "id": "B1RPviYi4GF",
          "output": {
            "nodeId": "ByjxPjtoVMt",
            "pinKey": "B1gN80uHvk-"
          },
          "input": {
            "nodeId": "HJDbPits4zt",
            "pinKey": "HJCfI0dBDkb-$4"
          }
        },
        "HJy_PsYsEMt": {
          "id": "HJy_PsYsEMt",
          "output": {
            "nodeId": "BJhgwoFo4Gt",
            "pinKey": "B1gN80uHvk-"
          },
          "input": {
            "nodeId": "HJDbPits4zt",
            "pinKey": "HJCfI0dBDkb-$5"
          }
        },
        "r1e_DiFiNzY": {
          "id": "r1e_DiFiNzY",
          "output": {
            "nodeId": "BJhgwoFo4Gt",
            "pinKey": "B1gN80uHvk-"
          },
          "input": {
            "nodeId": "H1z-wstiNzK",
            "pinKey": "rJUjrCTUb-$5"
          }
        },
        "SJWuvits4fF": {
          "id": "SJWuvits4fF",
          "output": {
            "nodeId": "Sk6ewitsNfK",
            "pinKey": "B1gN80uHvk-"
          },
          "input": {
            "nodeId": "HJDbPits4zt",
            "pinKey": "HJCfI0dBDkb-$6"
          }
        },
        "S1MuwjtsVfY": {
          "id": "S1MuwjtsVfY",
          "output": {
            "nodeId": "Sk6ewitsNfK",
            "pinKey": "B1gN80uHvk-"
          },
          "input": {
            "nodeId": "H1z-wstiNzK",
            "pinKey": "rJUjrCTUb-$6"
          }
        },
        "rJQdvjKoVMK": {
          "id": "rJQdvjKoVMK",
          "output": {
            "nodeId": "r18gwjtsNGt",
            "pinKey": "B1gN80uHvk-"
          },
          "input": {
            "nodeId": "H1z-wstiNzK",
            "pinKey": "rJUjrCTUb-$7"
          }
        },
        "rkNOvsYj4GK": {
          "id": "rkNOvsYj4GK",
          "output": {
            "nodeId": "r18gwjtsNGt",
            "pinKey": "B1gN80uHvk-"
          },
          "input": {
            "nodeId": "HJDbPits4zt",
            "pinKey": "HJCfI0dBDkb-$7"
          }
        },
        "BJBuDjKo4MY": {
          "id": "BJBuDjKo4MY",
          "output": {
            "nodeId": "Skvlwots4GK",
            "pinKey": "B1gN80uHvk-"
          },
          "input": {
            "nodeId": "HJDbPits4zt",
            "pinKey": "HJCfI0dBDkb-$8"
          }
        },
        "SkUOPiYiNzF": {
          "id": "SkUOPiYiNzF",
          "output": {
            "nodeId": "Skvlwots4GK",
            "pinKey": "B1gN80uHvk-"
          },
          "input": {
            "nodeId": "H1z-wstiNzK",
            "pinKey": "rJUjrCTUb-$8"
          }
        },
        "S1vOvsYjVGY": {
          "id": "S1vOvsYjVGY",
          "output": {
            "nodeId": "HkdlviFjEfF",
            "pinKey": "B1gN80uHvk-"
          },
          "input": {
            "nodeId": "HJDbPits4zt",
            "pinKey": "HJCfI0dBDkb-$9"
          }
        },
        "rkO_vsYsVfF": {
          "id": "rkO_vsYsVfF",
          "output": {
            "nodeId": "HkdlviFjEfF",
            "pinKey": "B1gN80uHvk-"
          },
          "input": {
            "nodeId": "H1z-wstiNzK",
            "pinKey": "rJUjrCTUb-$9"
          }
        },
        "rkY_woKj4GY": {
          "id": "rkY_woKj4GY",
          "output": {
            "nodeId": "HJYgDoKjNzY",
            "pinKey": "B1gN80uHvk-"
          },
          "input": {
            "nodeId": "HJDbPits4zt",
            "pinKey": "HJCfI0dBDkb-$10"
          }
        },
        "BJ5OPstiNzF": {
          "id": "BJ5OPstiNzF",
          "output": {
            "nodeId": "HJYgDoKjNzY",
            "pinKey": "B1gN80uHvk-"
          },
          "input": {
            "nodeId": "H1z-wstiNzK",
            "pinKey": "rJUjrCTUb-$10"
          }
        },
        "Bki_viYiVGF": {
          "id": "Bki_viYiVGF",
          "output": {
            "nodeId": "BkSeviYiNft",
            "pinKey": "B1gN80uHvk-"
          },
          "input": {
            "nodeId": "HJDbPits4zt",
            "pinKey": "HJCfI0dBDkb-$14"
          }
        },
        "H12OvoYj4MK": {
          "id": "H12OvoYj4MK",
          "output": {
            "nodeId": "BkSeviYiNft",
            "pinKey": "B1gN80uHvk-"
          },
          "input": {
            "nodeId": "H1z-wstiNzK",
            "pinKey": "rJUjrCTUb-$14"
          }
        },
        "HJpODsYjVMY": {
          "id": "HJpODsYjVMY",
          "output": {
            "nodeId": "HJzewoFiNMK",
            "pinKey": "B1gN80uHvk-"
          },
          "input": {
            "nodeId": "H1z-wstiNzK",
            "pinKey": "rJUjrCTUb-$11"
          }
        },
        "HyRuvjYsVMF": {
          "id": "HyRuvjYsVMF",
          "output": {
            "nodeId": "HJzewoFiNMK",
            "pinKey": "B1gN80uHvk-"
          },
          "input": {
            "nodeId": "HJDbPits4zt",
            "pinKey": "HJCfI0dBDkb-$11"
          }
        },
        "Sk1twoKsEfF": {
          "id": "Sk1twoKsEfF",
          "output": {
            "nodeId": "BkQgvitjEMK",
            "pinKey": "B1gN80uHvk-"
          },
          "input": {
            "nodeId": "H1z-wstiNzK",
            "pinKey": "rJUjrCTUb-$12"
          }
        },
        "rkgYvoFo4Mt": {
          "id": "rkgYvoFo4Mt",
          "output": {
            "nodeId": "BkQgvitjEMK",
            "pinKey": "B1gN80uHvk-"
          },
          "input": {
            "nodeId": "HJDbPits4zt",
            "pinKey": "HJCfI0dBDkb-$12"
          }
        },
        "B1bYvjYoVzK": {
          "id": "B1bYvjYoVzK",
          "output": {
            "nodeId": "HJNewsFsEzY",
            "pinKey": "B1gN80uHvk-"
          },
          "input": {
            "nodeId": "HJDbPits4zt",
            "pinKey": "HJCfI0dBDkb-$13"
          }
        },
        "HJzFPsKsEGK": {
          "id": "HJzFPsKsEGK",
          "output": {
            "nodeId": "HJNewsFsEzY",
            "pinKey": "B1gN80uHvk-"
          },
          "input": {
            "nodeId": "H1z-wstiNzK",
            "pinKey": "rJUjrCTUb-$13"
          }
        },
        "SJoQqs4MF": {
          "id": "SJoQqs4MF",
          "output": {
            "nodeId": "ByBQ9oNMK",
            "pinKey": "__out__"
          },
          "input": {
            "nodeId": "HJDoFo4zK",
            "pinKey": "rJjXFA9JQ"
          }
        },
        "S1CNqsNft": {
          "id": "S1CNqsNft",
          "output": {
            "nodeId": "rkINqiNfY",
            "pinKey": "__out__"
          },
          "input": {
            "nodeId": "SkgDoFo4Gt",
            "pinKey": "rJjXFA9JQ"
          }
        },
        "BkCr9i4MF": {
          "id": "BkCr9i4MF",
          "output": {
            "nodeId": "SkdH5o4GK",
            "pinKey": "__out__"
          },
          "input": {
            "nodeId": "BJWviKsNMK",
            "pinKey": "rJjXFA9JQ"
          }
        },
        "r1iI9iEzY": {
          "id": "r1iI9iEzY",
          "output": {
            "nodeId": "HyBU9jNzK",
            "pinKey": "__out__"
          },
          "input": {
            "nodeId": "BJGDsKiEfF",
            "pinKey": "rJjXFA9JQ"
          }
        },
        "rJx_cjVfK": {
          "id": "rJx_cjVfK",
          "output": {
            "nodeId": "SJvP9i4MY",
            "pinKey": "__out__"
          },
          "input": {
            "nodeId": "HkCPjFsEMK",
            "pinKey": "ByNiWkt8Z"
          }
        },
        "rkKt5iNzY": {
          "id": "rkKt5iNzY",
          "output": {
            "nodeId": "Sy7FciNfK",
            "pinKey": "__out__"
          },
          "input": {
            "nodeId": "SkJgDsKi4fF",
            "pinKey": "ByNiWkt8Z"
          }
        },
        "SJn9cjEMF": {
          "id": "SJn9cjEMF",
          "output": {
            "nodeId": "HyP55oVMF",
            "pinKey": "__out__"
          },
          "input": {
            "nodeId": "HygevjtjEzY",
            "pinKey": "ByNiWkt8Z"
          }
        },
        "S1cs9j4GF": {
          "id": "S1cs9j4GF",
          "output": {
            "nodeId": "HJHjcsNMY",
            "pinKey": "__out__"
          },
          "input": {
            "nodeId": "SkZgDsYoEMt",
            "pinKey": "ByNiWkt8Z"
          }
        },
        "SJ0yosVzF": {
          "id": "SJ0yosVzF",
          "output": {
            "nodeId": "S1mbPsto4MF",
            "pinKey": "S13xLCuHvkW"
          },
          "input": {
            "nodeId": "HkmJooNzt",
            "pinKey": "__in__"
          }
        }
      },
      "nodes": {
        "HJDoFo4zK": {
          "boundLiterals": {
            "rJjXFA9JQ": "D6",
            "BygApTqym": "Continuously",
            "HJ6HsEngZ": "True"
          },
          "id": "HJDoFo4zK",
          "type": "xod/gpio/digital-write",
          "position": {
            "x": 6,
            "y": 1.75,
            "units": "slots"
          }
        },
        "SkgDoFo4Gt": {
          "boundLiterals": {
            "rJjXFA9JQ": "D7",
            "HJ6HsEngZ": "True"
          },
          "id": "SkgDoFo4Gt",
          "type": "xod/gpio/digital-write",
          "position": {
            "x": 6,
            "y": 3.75,
            "units": "slots"
          }
        },
        "BJWviKsNMK": {
          "boundLiterals": {
            "rJjXFA9JQ": "D8",
            "HJ6HsEngZ": "True"
          },
          "id": "BJWviKsNMK",
          "type": "xod/gpio/digital-write",
          "position": {
            "x": 6,
            "y": 5.75,
            "units": "slots"
          }
        },
        "BJGDsKiEfF": {
          "boundLiterals": {
            "rJjXFA9JQ": "D9",
            "HJ6HsEngZ": "True"
          },
          "id": "BJGDsKiEfF",
          "type": "xod/gpio/digital-write",
          "position": {
            "x": 6,
            "y": 7.75,
            "units": "slots"
          }
        },
        "HJ7wsYiVzt": {
          "boundLiterals": {
            "Skre8ROSv1-": "0.05",
            "HkU3vNoTW": "False"
          },
          "id": "HJ7wsYiVzt",
          "type": "xod/core/delay",
          "position": {
            "x": 2,
            "y": 1.75,
            "units": "slots"
          }
        },
        "r1VvjtiNzF": {
          "id": "r1VvjtiNzF",
          "type": "xod/core/not",
          "position": {
            "x": 5,
            "y": 1.75,
            "units": "slots"
          }
        },
        "BkrvsYiVft": {
          "boundLiterals": {
            "Skre8ROSv1-": "0.05",
            "HkU3vNoTW": "False"
          },
          "id": "BkrvsYiVft",
          "type": "xod/core/delay",
          "position": {
            "x": 2,
            "y": 3.75,
            "units": "slots"
          }
        },
        "BkIDjYsNzY": {
          "id": "BkIDjYsNzY",
          "type": "xod/core/not",
          "position": {
            "x": 5,
            "y": 3.75,
            "units": "slots"
          }
        },
        "S1PvoKiNMt": {
          "boundLiterals": {
            "Skre8ROSv1-": "0.05",
            "HkU3vNoTW": "False"
          },
          "id": "S1PvoKiNMt",
          "type": "xod/core/delay",
          "position": {
            "x": 2,
            "y": 5.75,
            "units": "slots"
          }
        },
        "HJdPoYoNGK": {
          "id": "HJdPoYoNGK",
          "type": "xod/core/not",
          "position": {
            "x": 5,
            "y": 5.75,
            "units": "slots"
          }
        },
        "SJFDiYiNGF": {
          "boundLiterals": {
            "Skre8ROSv1-": "0.05",
            "HkU3vNoTW": "False"
          },
          "id": "SJFDiYiNGF",
          "type": "xod/core/delay",
          "position": {
            "x": 2,
            "y": 7.75,
            "units": "slots"
          }
        },
        "rycDoYo4Gt": {
          "id": "rycDoYo4Gt",
          "type": "xod/core/not",
          "position": {
            "x": 5,
            "y": 7.75,
            "units": "slots"
          }
        },
        "SJoDotsEGK": {
          "id": "SJoDotsEGK",
          "type": "xod/core/defer",
          "position": {
            "x": 0,
            "y": 3.75,
            "units": "slots"
          }
        },
        "Hk3PsFoVMF": {
          "id": "Hk3PsFoVMF",
          "type": "xod/core/any",
          "position": {
            "x": 2,
            "y": 0.75,
            "units": "slots"
          }
        },
        "SyTPoFj4MF": {
          "id": "SyTPoFj4MF",
          "type": "xod/core/boot",
          "position": {
            "x": 3,
            "y": -0.25,
            "units": "slots"
          }
        },
        "HkCPjFsEMK": {
          "boundLiterals": {
            "ByNiWkt8Z": "D2"
          },
          "id": "HkCPjFsEMK",
          "type": "xod/common-hardware/button",
          "position": {
            "x": 22,
            "y": 1.75,
            "units": "slots"
          }
        },
        "SkJgDsKi4fF": {
          "boundLiterals": {
            "ByNiWkt8Z": "D3"
          },
          "id": "SkJgDsKi4fF",
          "type": "xod/common-hardware/button",
          "position": {
            "x": 22,
            "y": 3.75,
            "units": "slots"
          }
        },
        "HygevjtjEzY": {
          "boundLiterals": {
            "ByNiWkt8Z": "D4"
          },
          "id": "HygevjtjEzY",
          "type": "xod/common-hardware/button",
          "position": {
            "x": 22,
            "y": 5.75,
            "units": "slots"
          }
        },
        "SkZgDsYoEMt": {
          "boundLiterals": {
            "ByNiWkt8Z": "D5"
          },
          "id": "SkZgDsYoEMt",
          "type": "xod/common-hardware/button",
          "position": {
            "x": 22,
            "y": 7.75,
            "units": "slots"
          }
        },
        "HJzewoFiNMK": {
          "label": "D",
          "id": "HJzewoFiNMK",
          "type": "xod/core/and",
          "position": {
            "x": 10,
            "y": 1.75,
            "units": "slots"
          }
        },
        "BkQgvitjEMK": {
          "label": "#",
          "id": "BkQgvitjEMK",
          "type": "xod/core/and",
          "position": {
            "x": 13,
            "y": 1.75,
            "units": "slots"
          }
        },
        "HJNewsFsEzY": {
          "label": "0",
          "id": "HJNewsFsEzY",
          "type": "xod/core/and",
          "position": {
            "x": 16,
            "y": 1.75,
            "units": "slots"
          }
        },
        "BkSeviYiNft": {
          "label": "*",
          "id": "BkSeviYiNft",
          "type": "xod/core/and",
          "position": {
            "x": 19,
            "y": 1.75,
            "units": "slots"
          }
        },
        "r18gwjtsNGt": {
          "label": "C",
          "id": "r18gwjtsNGt",
          "type": "xod/core/and",
          "position": {
            "x": 10,
            "y": 3.75,
            "units": "slots"
          }
        },
        "Skvlwots4GK": {
          "label": "9",
          "id": "Skvlwots4GK",
          "type": "xod/core/and",
          "position": {
            "x": 13,
            "y": 3.75,
            "units": "slots"
          }
        },
        "HkdlviFjEfF": {
          "label": "8",
          "id": "HkdlviFjEfF",
          "type": "xod/core/and",
          "position": {
            "x": 16,
            "y": 3.75,
            "units": "slots"
          }
        },
        "HJYgDoKjNzY": {
          "label": "7",
          "id": "HJYgDoKjNzY",
          "type": "xod/core/and",
          "position": {
            "x": 19,
            "y": 3.75,
            "units": "slots"
          }
        },
        "HJqxDsKs4fF": {
          "label": "B",
          "id": "HJqxDsKs4fF",
          "type": "xod/core/and",
          "position": {
            "x": 10,
            "y": 5.75,
            "units": "slots"
          }
        },
        "ByjxPjtoVMt": {
          "label": "6",
          "id": "ByjxPjtoVMt",
          "type": "xod/core/and",
          "position": {
            "x": 13,
            "y": 5.75,
            "units": "slots"
          }
        },
        "BJhgwoFo4Gt": {
          "label": "5",
          "id": "BJhgwoFo4Gt",
          "type": "xod/core/and",
          "position": {
            "x": 16,
            "y": 5.75,
            "units": "slots"
          }
        },
        "Sk6ewitsNfK": {
          "label": "4",
          "id": "Sk6ewitsNfK",
          "type": "xod/core/and",
          "position": {
            "x": 19,
            "y": 5.75,
            "units": "slots"
          }
        },
        "rJRePsFsNfY": {
          "label": "A",
          "id": "rJRePsFsNfY",
          "type": "xod/core/and",
          "position": {
            "x": 10,
            "y": 7.75,
            "units": "slots"
          }
        },
        "BJ1ZPotsVfK": {
          "label": "3",
          "id": "BJ1ZPotsVfK",
          "type": "xod/core/and",
          "position": {
            "x": 13,
            "y": 7.75,
            "units": "slots"
          }
        },
        "r1l-DjFoNGF": {
          "label": "2",
          "id": "r1l-DjFoNGF",
          "type": "xod/core/and",
          "position": {
            "x": 16,
            "y": 7.75,
            "units": "slots"
          }
        },
        "B1--PjKiVGY": {
          "label": "1",
          "id": "B1--PjKiVGY",
          "type": "xod/core/and",
          "position": {
            "x": 19,
            "y": 7.75,
            "units": "slots"
          }
        },
        "H1z-wstiNzK": {
          "arityLevel": 15,
          "id": "H1z-wstiNzK",
          "type": "xod/core/select",
          "position": {
            "x": 4,
            "y": 12.75,
            "units": "slots"
          }
        },
        "S1mbPsto4MF": {
          "id": "S1mbPsto4MF",
          "type": "xod/core/if-else",
          "position": {
            "x": 3,
            "y": 14.75,
            "units": "slots"
          }
        },
        "B14-PjFo4GK": {
          "boundLiterals": {
            "B1x2RV3eZ": "\"@\""
          },
          "id": "B14-PjFo4GK",
          "type": "xod/core/constant-string",
          "position": {
            "x": 5,
            "y": 13.75,
            "units": "slots"
          }
        },
        "ryBWDsYiNGF": {
          "boundLiterals": {
            "B1x2RV3eZ": "\"A\""
          },
          "id": "ryBWDsYiNGF",
          "type": "xod/core/constant-string",
          "position": {
            "x": 4,
            "y": 11.75,
            "units": "slots"
          }
        },
        "BkUZvstiVfK": {
          "boundLiterals": {
            "B1x2RV3eZ": "\"3\""
          },
          "id": "BkUZvstiVfK",
          "type": "xod/core/constant-string",
          "position": {
            "x": 6,
            "y": 11.75,
            "units": "slots"
          }
        },
        "HJDbPits4zt": {
          "arityLevel": 15,
          "id": "HJDbPits4zt",
          "type": "xod/core/or",
          "position": {
            "x": 7,
            "y": 10.75,
            "units": "slots"
          }
        },
        "rytZvitoNzt": {
          "boundLiterals": {
            "Sk3hdlIMr": "0.5"
          },
          "id": "rytZvitoNzt",
          "type": "xod/core/overrun",
          "position": {
            "x": 1,
            "y": 11.75,
            "units": "slots"
          }
        },
        "Sk9WDoKiEzK": {
          "boundLiterals": {
            "B1x2RV3eZ": "\"2\""
          },
          "id": "Sk9WDoKiEzK",
          "type": "xod/core/constant-string",
          "position": {
            "x": 8,
            "y": 11.75,
            "units": "slots"
          }
        },
        "rkobDoFsNft": {
          "boundLiterals": {
            "B1x2RV3eZ": "\"1\""
          },
          "id": "rkobDoFsNft",
          "type": "xod/core/constant-string",
          "position": {
            "x": 10,
            "y": 11.75,
            "units": "slots"
          }
        },
        "Bk3ZPits4GY": {
          "boundLiterals": {
            "B1x2RV3eZ": "\"B\""
          },
          "id": "Bk3ZPits4GY",
          "type": "xod/core/constant-string",
          "position": {
            "x": 12,
            "y": 11.75,
            "units": "slots"
          }
        },
        "S1a-woFs4GY": {
          "boundLiterals": {
            "B1x2RV3eZ": "\"6\""
          },
          "id": "S1a-woFs4GY",
          "type": "xod/core/constant-string",
          "position": {
            "x": 14,
            "y": 11.75,
            "units": "slots"
          }
        },
        "SyRbvitsNGY": {
          "boundLiterals": {
            "B1x2RV3eZ": "\"5\""
          },
          "id": "SyRbvitsNGY",
          "type": "xod/core/constant-string",
          "position": {
            "x": 16,
            "y": 11.75,
            "units": "slots"
          }
        },
        "rJJzwjYoVMK": {
          "boundLiterals": {
            "B1x2RV3eZ": "\"4\""
          },
          "id": "rJJzwjYoVMK",
          "type": "xod/core/constant-string",
          "position": {
            "x": 18,
            "y": 11.75,
            "units": "slots"
          }
        },
        "BklGwsYoVfF": {
          "boundLiterals": {
            "B1x2RV3eZ": "\"C\""
          },
          "id": "BklGwsYoVfF",
          "type": "xod/core/constant-string",
          "position": {
            "x": 20,
            "y": 11.75,
            "units": "slots"
          }
        },
        "ByZzwsYjEMK": {
          "boundLiterals": {
            "B1x2RV3eZ": "\"9\""
          },
          "id": "ByZzwsYjEMK",
          "type": "xod/core/constant-string",
          "position": {
            "x": 22,
            "y": 11.75,
            "units": "slots"
          }
        },
        "H1fzviFi4zY": {
          "boundLiterals": {
            "B1x2RV3eZ": "\"8\""
          },
          "id": "H1fzviFi4zY",
          "type": "xod/core/constant-string",
          "position": {
            "x": 24,
            "y": 11.75,
            "units": "slots"
          }
        },
        "H1XGDiFoVGY": {
          "boundLiterals": {
            "B1x2RV3eZ": "\"7\""
          },
          "id": "H1XGDiFoVGY",
          "type": "xod/core/constant-string",
          "position": {
            "x": 26,
            "y": 11.75,
            "units": "slots"
          }
        },
        "S1VfwjtjNzY": {
          "boundLiterals": {
            "B1x2RV3eZ": "\"D\""
          },
          "id": "S1VfwjtjNzY",
          "type": "xod/core/constant-string",
          "position": {
            "x": 28,
            "y": 11.75,
            "units": "slots"
          }
        },
        "rJSzwiFsVfY": {
          "boundLiterals": {
            "B1x2RV3eZ": "\"#\""
          },
          "id": "rJSzwiFsVfY",
          "type": "xod/core/constant-string",
          "position": {
            "x": 30,
            "y": 11.75,
            "units": "slots"
          }
        },
        "S1UfDsYoNGF": {
          "boundLiterals": {
            "B1x2RV3eZ": "\"0\""
          },
          "id": "S1UfDsYoNGF",
          "type": "xod/core/constant-string",
          "position": {
            "x": 32,
            "y": 11.75,
            "units": "slots"
          }
        },
        "H1PzviKsVMF": {
          "boundLiterals": {
            "B1x2RV3eZ": "\"*\""
          },
          "id": "H1PzviKsVMF",
          "type": "xod/core/constant-string",
          "position": {
            "x": 34,
            "y": 11.75,
            "units": "slots"
          }
        },
        "H1_zvjto4zY": {
          "boundLiterals": {
            "Skre8ROSv1-": "0.05",
            "HkU3vNoTW": "False"
          },
          "id": "H1_zvjto4zY",
          "type": "xod/core/delay",
          "position": {
            "x": 4,
            "y": 2.75,
            "units": "slots"
          }
        },
        "ryKfvsts4GK": {
          "boundLiterals": {
            "Skre8ROSv1-": "0.05",
            "HkU3vNoTW": "False"
          },
          "id": "ryKfvsts4GK",
          "type": "xod/core/delay",
          "position": {
            "x": 4,
            "y": 4.75,
            "units": "slots"
          }
        },
        "S19MPjtsEGK": {
          "boundLiterals": {
            "Skre8ROSv1-": "0.05",
            "HkU3vNoTW": "False"
          },
          "id": "S19MPjtsEGK",
          "type": "xod/core/delay",
          "position": {
            "x": 4,
            "y": 6.75,
            "units": "slots"
          }
        },
        "SyiGPjYoEGK": {
          "boundLiterals": {
            "Skre8ROSv1-": "0.05",
            "HkU3vNoTW": "False"
          },
          "id": "SyiGPjYoEGK",
          "type": "xod/core/delay",
          "position": {
            "x": 4,
            "y": 8.75,
            "units": "slots"
          }
        },
        "ByBQ9oNMK": {
          "label": "o1",
          "id": "ByBQ9oNMK",
          "type": "xod/patch-nodes/input-port",
          "position": {
            "x": 8,
            "y": 1,
            "units": "slots"
          }
        },
        "rkINqiNfY": {
          "label": "o2",
          "id": "rkINqiNfY",
          "type": "xod/patch-nodes/input-port",
          "position": {
            "x": 8,
            "y": 3,
            "units": "slots"
          }
        },
        "SkdH5o4GK": {
          "label": "o3",
          "id": "SkdH5o4GK",
          "type": "xod/patch-nodes/input-port",
          "position": {
            "x": 8,
            "y": 5,
            "units": "slots"
          }
        },
        "HyBU9jNzK": {
          "label": "o4",
          "id": "HyBU9jNzK",
          "type": "xod/patch-nodes/input-port",
          "position": {
            "x": 8,
            "y": 7,
            "units": "slots"
          }
        },
        "SJvP9i4MY": {
          "label": "i1",
          "id": "SJvP9i4MY",
          "type": "xod/patch-nodes/input-port",
          "position": {
            "x": 23,
            "y": 1,
            "units": "slots"
          }
        },
        "Sy7FciNfK": {
          "label": "i2",
          "id": "Sy7FciNfK",
          "type": "xod/patch-nodes/input-port",
          "position": {
            "x": 23,
            "y": 3,
            "units": "slots"
          }
        },
        "HyP55oVMF": {
          "label": "i3",
          "id": "HyP55oVMF",
          "type": "xod/patch-nodes/input-port",
          "position": {
            "x": 23,
            "y": 5,
            "units": "slots"
          }
        },
        "HJHjcsNMY": {
          "label": "i4",
          "id": "HJHjcsNMY",
          "type": "xod/patch-nodes/input-port",
          "position": {
            "x": 23,
            "y": 7,
            "units": "slots"
          }
        },
        "HkmJooNzt": {
          "id": "HkmJooNzt",
          "type": "xod/patch-nodes/output-string",
          "position": {
            "x": 3,
            "y": 16,
            "units": "slots"
          }
        }
      },
      "path": "@/keyboard4x4"
    }
  },
  "name": "key4x4"
}
