{
  "description": "Time-of-Flight (ToF) sensor. Arduino library for the ST VL53L1X sensor (https://www.st.com/en/imaging-and-photonics-solutions/vl53l1x.html). Wraps the  Pololu VL43L1X library for Arduino  (https://github.com/pololu/vl53l1x-arduino).",
  "license": "BSD-3-Clause",
  "name": "vl53l1x-time-of-flight",
  "patches": {
    "@/example-output-to-oled": {
      "description": "Example demonstrating output of range measurement to an OLED screen. ",
      "links": {
        "By1xjhnjzCE": {
          "id": "By1xjhnjzCE",
          "input": {
            "nodeId": "S1ohnizRE",
            "pinKey": "S1mxGvKUN"
          },
          "output": {
            "nodeId": "BySi32izA4",
            "pinKey": "__out__"
          }
        },
        "ByRsh3oGCV": {
          "id": "ByRsh3oGCV",
          "input": {
            "nodeId": "Skgih2jzCE",
            "pinKey": "SJDbf_YUV"
          },
          "output": {
            "nodeId": "BkIsnnjf0N",
            "pinKey": "r1DL6CFU4"
          }
        },
        "Hk9s22jzCN": {
          "id": "Hk9s22jzCN",
          "input": {
            "nodeId": "H14o22oMAE",
            "pinKey": "__in__"
          },
          "output": {
            "nodeId": "r1Xj3hszCE",
            "pinKey": "ryH6tSt8N"
          }
        },
        "Hko8VhzAV": {
          "id": "Hko8VhzAV",
          "input": {
            "nodeId": "rkruQnfCV",
            "pinKey": "r1AgIROHDJW"
          },
          "output": {
            "nodeId": "ByhHVnMA4",
            "pinKey": "B1x2RV3eZ"
          }
        },
        "S16A7hzRE": {
          "id": "S16A7hzRE",
          "input": {
            "nodeId": "BkUnxhMCE",
            "pinKey": "BJlHojaWZ"
          },
          "output": {
            "nodeId": "rJvJTszAE",
            "pinKey": "HJYZ2P-RN"
          }
        },
        "S1io22jGAV": {
          "id": "S1io22jGAV",
          "input": {
            "nodeId": "BkIsnnjf0N",
            "pinKey": "B11QT1qLN"
          },
          "output": {
            "nodeId": "S1ohnizRE",
            "pinKey": "rylSGPt8E"
          }
        },
        "S1toQhG0N": {
          "id": "S1toQhG0N",
          "input": {
            "nodeId": "Bytc73GAE",
            "pinKey": "rJXICuSwyW"
          },
          "output": {
            "nodeId": "rJvJTszAE",
            "pinKey": "ByIZfnw-RV"
          }
        },
        "SJash2iMAN": {
          "id": "SJash2iMAN",
          "input": {
            "nodeId": "BkIsnnjf0N",
            "pinKey": "HJIQ6AY8E"
          },
          "output": {
            "nodeId": "Bkvj32ozAE",
            "pinKey": "__out__"
          }
        },
        "SJbNEhz0E": {
          "id": "SJbNEhz0E",
          "input": {
            "nodeId": "BkIsnnjf0N",
            "pinKey": "S1gH6CKIN"
          },
          "output": {
            "nodeId": "rkruQnfCV",
            "pinKey": "S13xLCuHvkW"
          }
        },
        "Sk2o2hoGR4": {
          "id": "Sk2o2hoGR4",
          "input": {
            "nodeId": "Skgih2jzCE",
            "pinKey": "Sy6LZuYIE"
          },
          "output": {
            "nodeId": "SydshnszAN",
            "pinKey": "__out__"
          }
        },
        "Sk7VE3f0E": {
          "id": "Sk7VE3f0E",
          "input": {
            "nodeId": "rkruQnfCV",
            "pinKey": "ryTeUROHD1b"
          },
          "output": {
            "nodeId": "SkrtRjf04",
            "pinKey": "rksccsp-W"
          }
        },
        "Sybwyaiz0N": {
          "id": "Sybwyaiz0N",
          "input": {
            "nodeId": "rJvJTszAE",
            "pinKey": "H1kEDPWCN"
          },
          "output": {
            "nodeId": "BkeDJaiz0E",
            "pinKey": "HJU8CE2lW"
          }
        },
        "r1VIN2zC4": {
          "id": "r1VIN2zC4",
          "input": {
            "nodeId": "rkruQnfCV",
            "pinKey": "S1yZIA_rDJZ"
          },
          "output": {
            "nodeId": "Bytc73GAE",
            "pinKey": "H1E8AuSPkZ"
          }
        },
        "r1vQEnGRE": {
          "id": "r1vQEnGRE",
          "input": {
            "nodeId": "SkrtRjf04",
            "pinKey": "Hkqu9oaWb"
          },
          "output": {
            "nodeId": "BkUnxhMCE",
            "pinKey": "r1H_oipZb"
          }
        },
        "rkLPToGRV": {
          "id": "rkLPToGRV",
          "input": {
            "nodeId": "S1ohnizRE",
            "pinKey": "r1H7MwK8E"
          },
          "output": {
            "nodeId": "rJvJTszAE",
            "pinKey": "ByI12D-AE"
          }
        }
      },
      "nodes": {
        "BkIsnnjf0N": {
          "boundLiterals": {
            "Bkw-6yqI4": "10",
            "ByW_2k9IN": "03h",
            "Hypl61qUE": "10",
            "S1gH6CKIN": "\"XOD\""
          },
          "id": "BkIsnnjf0N",
          "position": {
            "x": 0,
            "y": 6,
            "units": "slots"
          },
          "type": "wayland/ssd1306-oled-i2c/draw-text"
        },
        "BkUnxhMCE": {
          "boundLiterals": {
            "HJTIija-W": "0"
          },
          "id": "BkUnxhMCE",
          "position": {
            "x": 4,
            "y": 3,
            "units": "slots"
          },
          "type": "xod/core/format-number"
        },
        "BkeDJaiz0E": {
          "boundLiterals": {
            "B13SCNhl-": "0.25"
          },
          "id": "BkeDJaiz0E",
          "position": {
            "x": 10,
            "y": 1,
            "units": "slots"
          },
          "type": "xod/core/clock"
        },
        "Bkvj32ozAE": {
          "id": "Bkvj32ozAE",
          "label": "DEV",
          "position": {
            "x": -1,
            "y": 6,
            "units": "slots"
          },
          "type": "xod/patch-nodes/from-bus"
        },
        "BySi32izA4": {
          "id": "BySi32izA4",
          "label": "DEV",
          "position": {
            "x": 7,
            "y": 4,
            "units": "slots"
          },
          "type": "xod/patch-nodes/from-bus"
        },
        "ByhHVnMA4": {
          "boundLiterals": {
            "B1x2RV3eZ": "\"NA\""
          },
          "id": "ByhHVnMA4",
          "position": {
            "x": 6,
            "y": 4,
            "units": "slots"
          },
          "type": "xod/core/constant-string"
        },
        "Bytc73GAE": {
          "boundLiterals": {
            "HJG8C_SPkb": "0"
          },
          "id": "Bytc73GAE",
          "position": {
            "x": 6,
            "y": 3,
            "units": "slots"
          },
          "type": "xod/core/equal"
        },
        "H14o22oMAE": {
          "id": "H14o22oMAE",
          "label": "DEV",
          "position": {
            "x": 0,
            "y": 5,
            "units": "slots"
          },
          "type": "xod/patch-nodes/to-bus"
        },
        "S1ohnizRE": {
          "id": "S1ohnizRE",
          "position": {
            "x": 7,
            "y": 5,
            "units": "slots"
          },
          "type": "wayland/ssd1306-oled-i2c/clear-display"
        },
        "Skgih2jzCE": {
          "id": "Skgih2jzCE",
          "position": {
            "x": 0,
            "y": 7,
            "units": "slots"
          },
          "type": "wayland/ssd1306-oled-i2c/send-buffer-to-display"
        },
        "SkrtRjf04": {
          "boundLiterals": {
            "BkeKcj6ZZ": "\"mm\""
          },
          "id": "SkrtRjf04",
          "position": {
            "x": 4,
            "y": 4,
            "units": "slots"
          },
          "type": "xod/core/concat"
        },
        "SydshnszAN": {
          "id": "SydshnszAN",
          "label": "DEV",
          "position": {
            "x": -1,
            "y": 7,
            "units": "slots"
          },
          "type": "xod/patch-nodes/from-bus"
        },
        "r1Xj3hszCE": {
          "id": "r1Xj3hszCE",
          "position": {
            "x": 0,
            "y": 4,
            "units": "slots"
          },
          "type": "wayland/ssd1306-oled-i2c/ssd1306-oled-i2c-device"
        },
        "rJvJTszAE": {
          "boundLiterals": {
            "HyXnQ_-04": "02h",
            "rJEHaGLRD": "4",
            "BJYBaGUAP": "4"
          },
          "id": "rJvJTszAE",
          "position": {
            "x": 4,
            "y": 2,
            "units": "slots"
          },
          "type": "@/tof-sensor"
        },
        "rkruQnfCV": {
          "boundLiterals": {
            "r1AgIROHDJW": "NA"
          },
          "id": "rkruQnfCV",
          "position": {
            "x": 3,
            "y": 5,
            "units": "slots"
          },
          "type": "xod/core/if-else"
        }
      },
      "path": "@/example-output-to-oled"
    },
    "@/example-set-address": {
      "comments": {
        "By6JbE80w": {
          "id": "By6JbE80w",
          "position": {
            "x": 12,
            "y": -1,
            "units": "slots"
          },
          "size": {
            "width": 14,
            "height": 4,
            "units": "slots"
          },
          "content": "The default I²C address of the VL53L1X device is 29h. You can change the I²C address of the device using the set-address node. If the device is reset the I²C address will return to the default. In this example we use a relay to cut the power to the VL53L1X to reset it, before initialization. If we were to reset the microcontroller board without resetting the VL53L1X we would only be able to run the patch once. \n\nOn the first run the address of the VL53L1X would be set to 30h. If the microcontroller board was then reset, the patch would run again from the beginning. However, if the VL53L1X continued to be powered on, then it would retain its new address of 30h. Initialization would fail on the 2nd run of the patch, because the init node expects the VL53L1X to have the default address of 29h, but it would actually be 30h.\n\nPolulu breakout boards for the VL53L1X have an XSHUT pin which enables them to be toggled on and off to facilitate address setting (see https://forum.pololu.com/t/vl53l1x-cant-change-address/18270). However the Pimoroni breakout board that I have used to develop this library doesn't have an XSHUT pin (or equivalent), so I had to use a relay to toggle it off and on. "
        }
      },
      "description": "Patch to demonstrate setting of I²C address.",
      "links": {
        "B1ds5kKaD": {
          "id": "B1ds5kKaD",
          "input": {
            "nodeId": "B13irJtpP",
            "pinKey": "HkGJ5u4np4"
          },
          "output": {
            "nodeId": "By4jrJKTP",
            "pinKey": "BydbeeW6D"
          }
        },
        "BJhnq1tpP": {
          "id": "BJhnq1tpP",
          "input": {
            "nodeId": "B13irJtpP",
            "pinKey": "Skey5dNnTV"
          },
          "output": {
            "nodeId": "rkO2q1FaP",
            "pinKey": "__out__"
          }
        },
        "By7h9kt6w": {
          "id": "By7h9kt6w",
          "input": {
            "nodeId": "H1Cj9yK6w",
            "pinKey": "HkXK-dGob"
          },
          "output": {
            "nodeId": "B13irJtpP",
            "pinKey": "B1uL9N36V"
          }
        },
        "HkQjcJK6P": {
          "id": "HkQjcJK6P",
          "input": {
            "nodeId": "By4jrJKTP",
            "pinKey": "r1sAygZ6v"
          },
          "output": {
            "nodeId": "BynXcJt6v",
            "pinKey": "S1qOGp9aN"
          }
        },
        "HkiY5JYpv": {
          "id": "HkiY5JYpv",
          "input": {
            "nodeId": "By4jrJKTP",
            "pinKey": "S1RHxeWTP"
          },
          "output": {
            "nodeId": "S1BF5kFpD",
            "pinKey": "__out__"
          }
        },
        "r1aw5kY6P": {
          "id": "r1aw5kY6P",
          "input": {
            "nodeId": "r1OP51KTP",
            "pinKey": "__in__"
          },
          "output": {
            "nodeId": "SkTcrJY6v",
            "pinKey": "HJSAd3qp4"
          }
        },
        "rJmt9JY6D": {
          "id": "rJmt9JY6D",
          "input": {
            "nodeId": "BynXcJt6v",
            "pinKey": "ByCrfT5TE"
          },
          "output": {
            "nodeId": "ryPOckYpv",
            "pinKey": "__out__"
          }
        },
        "ryQWBmICw": {
          "id": "ryQWBmICw",
          "output": {
            "nodeId": "SJ3lS7LRv",
            "pinKey": "B23RV3eJq"
          },
          "input": {
            "nodeId": "By4jrJKTP",
            "pinKey": "rkazegW6w"
          }
        },
        "HkLE1VU0w": {
          "id": "HkLE1VU0w",
          "output": {
            "nodeId": "HJ3X1ELCw",
            "pinKey": "Bk4gU0drwJ-"
          },
          "input": {
            "nodeId": "BynXcJt6v",
            "pinKey": "HkOwz69p4"
          }
        },
        "Bk6IJ4IRw": {
          "id": "Bk6IJ4IRw",
          "output": {
            "nodeId": "BkDmJVICw",
            "pinKey": "HkU3vNoTW"
          },
          "input": {
            "nodeId": "H1hG1NUCP",
            "pinKey": "SkgXWK4MB"
          }
        },
        "r1S1xNUCD": {
          "id": "r1S1xNUCD",
          "output": {
            "nodeId": "BkDmJVICw",
            "pinKey": "Bk4gU0drwJ-"
          },
          "input": {
            "nodeId": "HJ3X1ELCw",
            "pinKey": "SkSuD6LMb"
          }
        }
      },
      "nodes": {
        "B13irJtpP": {
          "id": "B13irJtpP",
          "position": {
            "x": 3,
            "y": 4,
            "units": "slots"
          },
          "type": "@/get-address"
        },
        "By4jrJKTP": {
          "id": "By4jrJKTP",
          "position": {
            "x": 4,
            "y": 3,
            "units": "slots"
          },
          "type": "@/set-address"
        },
        "BynXcJt6v": {
          "id": "BynXcJt6v",
          "position": {
            "x": 6,
            "y": 2,
            "units": "slots"
          },
          "type": "@/init"
        },
        "H1Cj9yK6w": {
          "id": "H1Cj9yK6w",
          "position": {
            "x": 3,
            "y": 5,
            "units": "slots"
          },
          "type": "xod/debug/watch"
        },
        "S1BF5kFpD": {
          "id": "S1BF5kFpD",
          "label": "DEV",
          "position": {
            "x": 4,
            "y": 2,
            "units": "slots"
          },
          "type": "xod/patch-nodes/from-bus"
        },
        "SkTcrJY6v": {
          "id": "SkTcrJY6v",
          "position": {
            "x": 3,
            "y": -1,
            "units": "slots"
          },
          "type": "@/vl53l1x-device"
        },
        "r1OP51KTP": {
          "id": "r1OP51KTP",
          "label": "DEV",
          "position": {
            "x": 3,
            "y": 0,
            "units": "slots"
          },
          "type": "xod/patch-nodes/to-bus"
        },
        "rkO2q1FaP": {
          "id": "rkO2q1FaP",
          "label": "DEV",
          "position": {
            "x": 3,
            "y": 3,
            "units": "slots"
          },
          "type": "xod/patch-nodes/from-bus"
        },
        "ryPOckYpv": {
          "id": "ryPOckYpv",
          "label": "DEV",
          "position": {
            "x": 6,
            "y": 1,
            "units": "slots"
          },
          "type": "xod/patch-nodes/from-bus"
        },
        "SJ3lS7LRv": {
          "id": "SJ3lS7LRv",
          "type": "xod/core/constant-byte",
          "position": {
            "x": 5,
            "y": -1,
            "units": "slots"
          },
          "boundLiterals": {
            "B23RV3eJq": "30h"
          }
        },
        "H1hG1NUCP": {
          "id": "H1hG1NUCP",
          "type": "xod/common-hardware/relay",
          "position": {
            "x": 8,
            "y": 0,
            "units": "slots"
          },
          "boundLiterals": {
            "SJdzbYEzH": "D3"
          }
        },
        "BkDmJVICw": {
          "id": "BkDmJVICw",
          "type": "xod/core/delay",
          "position": {
            "x": 8,
            "y": -1,
            "units": "slots"
          },
          "boundLiterals": {
            "Skre8ROSv1-": "1",
            "SkSuD6LMb": "On Boot"
          }
        },
        "HJ3X1ELCw": {
          "id": "HJ3X1ELCw",
          "type": "xod/core/delay",
          "position": {
            "x": 8,
            "y": 1,
            "units": "slots"
          },
          "boundLiterals": {
            "Skre8ROSv1-": "1"
          }
        }
      },
      "path": "@/example-set-address"
    },
    "@/example-test-configuration": {
      "description": "Patch to test nodes used to set and get configuration options.",
      "links": {
        "B1F1XqGCV": {
          "id": "B1F1XqGCV",
          "input": {
            "nodeId": "SkTRG9MAN",
            "pinKey": "S1e-F6VnTN"
          },
          "output": {
            "nodeId": "SkKIHnW04",
            "pinKey": "__out__"
          }
        },
        "B1MFHnZ0N": {
          "id": "B1MFHnZ0N",
          "input": {
            "nodeId": "r1s5G3-A4",
            "pinKey": "SygbNCw2TN"
          },
          "output": {
            "nodeId": "H1eDrnWAV",
            "pinKey": "__out__"
          }
        },
        "B1aFH3-CV": {
          "id": "B1aFH3-CV",
          "input": {
            "nodeId": "SJNz7nZ04",
            "pinKey": "SJIVEP-R4"
          },
          "output": {
            "nodeId": "HysIHhZ04",
            "pinKey": "__out__"
          }
        },
        "B1goIif04": {
          "id": "B1goIif04",
          "input": {
            "nodeId": "SkTRG9MAN",
            "pinKey": "SJzbFT436V"
          },
          "output": {
            "nodeId": "BJNaXh-04",
            "pinKey": "r1-HGlwnpN"
          }
        },
        "Bk3vjcD6v": {
          "id": "Bk3vjcD6v",
          "input": {
            "nodeId": "Sy2zj5Pav",
            "pinKey": "Bk4Lo5vaP"
          },
          "output": {
            "nodeId": "H1IN9d-C4",
            "pinKey": "HkWzLaShaE"
          }
        },
        "Bkzif3ZRN": {
          "id": "Bkzif3ZRN",
          "input": {
            "nodeId": "H1IN9d-C4",
            "pinKey": "BkGM8aBhaE"
          },
          "output": {
            "nodeId": "r1s5G3-A4",
            "pinKey": "r1ZbNRPn6V"
          }
        },
        "H1-YNnbA4": {
          "id": "H1-YNnbA4",
          "input": {
            "nodeId": "ByYPE3WRE",
            "pinKey": "HkXK-dGob"
          },
          "output": {
            "nodeId": "SJNz7nZ04",
            "pinKey": "S1UbNwb04"
          }
        },
        "H1XYNnbC4": {
          "id": "H1XYNnbC4",
          "input": {
            "nodeId": "rJqv4hbCE",
            "pinKey": "HkXK-dGob"
          },
          "output": {
            "nodeId": "BkuT72-C4",
            "pinKey": "r1QfgrPhTN"
          }
        },
        "H1e5t1K6D": {
          "id": "H1e5t1K6D",
          "input": {
            "nodeId": "rJquYkYpD",
            "pinKey": "ByCrfT5TE"
          },
          "output": {
            "nodeId": "HyuKtJY6w",
            "pinKey": "__out__"
          }
        },
        "HJ9Cj9w6D": {
          "id": "HJ9Cj9w6D",
          "input": {
            "nodeId": "rkVJscw6w",
            "pinKey": "Sycl6rbaD"
          },
          "output": {
            "nodeId": "SkTRG9MAN",
            "pinKey": "HJZbKp4h6E"
          }
        },
        "HJHYNnWCE": {
          "id": "HJHYNnWCE",
          "input": {
            "nodeId": "HJhwNnbAN",
            "pinKey": "HkXK-dGob"
          },
          "output": {
            "nodeId": "BJNaXh-04",
            "pinKey": "Sya7xwnpE"
          }
        },
        "HJbFB3bR4": {
          "id": "HJbFB3bR4",
          "input": {
            "nodeId": "H12NzhZCV",
            "pinKey": "ryeGjO_2TE"
          },
          "output": {
            "nodeId": "Bk0IBhb0E",
            "pinKey": "__out__"
          }
        },
        "Hk4cYkKpv": {
          "id": "Hk4cYkKpv",
          "input": {
            "nodeId": "H12NzhZCV",
            "pinKey": "H1GzouO364"
          },
          "output": {
            "nodeId": "rJquYkYpD",
            "pinKey": "S1qOGp9aN"
          }
        },
        "HykL4hZAE": {
          "id": "HykL4hZAE",
          "input": {
            "nodeId": "BJNaXh-04",
            "pinKey": "rkGHGlD3aE"
          },
          "output": {
            "nodeId": "BkuT72-C4",
            "pinKey": "rk-zgBD3pV"
          }
        },
        "SJH0s9Pav": {
          "id": "SJH0s9Pav",
          "input": {
            "nodeId": "BJI2o9w6P",
            "pinKey": "HkXK-dGob"
          },
          "output": {
            "nodeId": "rkVJscw6w",
            "pinKey": "H10vprb6w"
          }
        },
        "SJnjBcMRV": {
          "id": "SJnjBcMRV",
          "input": {
            "nodeId": "r1uU4nbCN",
            "pinKey": "HkXK-dGob"
          },
          "output": {
            "nodeId": "SkTRG9MAN",
            "pinKey": "ByYDjKZAE"
          }
        },
        "SkJoiqDTv": {
          "id": "SkJoiqDTv",
          "input": {
            "nodeId": "HJHqsqPpw",
            "pinKey": "Skey5dNnTV"
          },
          "output": {
            "nodeId": "ryK5i5DTP",
            "pinKey": "__out__"
          }
        },
        "SkumicDav": {
          "id": "SkumicDav",
          "input": {
            "nodeId": "Sy2zj5Pav",
            "pinKey": "HyPX8xbav"
          },
          "output": {
            "nodeId": "H1XQs5D6P",
            "pinKey": "__out__"
          }
        },
        "SyJHh5Dpw": {
          "id": "SyJHh5Dpw",
          "input": {
            "nodeId": "rkVJscw6w",
            "pinKey": "HJWkarWaP"
          },
          "output": {
            "nodeId": "HkY4n9DaP",
            "pinKey": "__out__"
          }
        },
        "SyVtH3ZAN": {
          "id": "SyVtH3ZAN",
          "input": {
            "nodeId": "H1IN9d-C4",
            "pinKey": "r1ezU6rhTV"
          },
          "output": {
            "nodeId": "BkeyvH2bCE",
            "pinKey": "__out__"
          }
        },
        "SydtSAdTD": {
          "id": "SydtSAdTD",
          "input": {
            "nodeId": "HJHqsqPpw",
            "pinKey": "HkGJ5u4np4"
          },
          "output": {
            "nodeId": "Sy2zj5Pav",
            "pinKey": "SJoNUx-6D"
          }
        },
        "SykofhZ0N": {
          "id": "SykofhZ0N",
          "input": {
            "nodeId": "r1s5G3-A4",
            "pinKey": "B1Mb4CwnaV"
          },
          "output": {
            "nodeId": "H12NzhZCV",
            "pinKey": "H1bGjOu2aN"
          }
        },
        "r1jH4h-R4": {
          "id": "r1jH4h-R4",
          "input": {
            "nodeId": "BkuT72-C4",
            "pinKey": "HkzfgBDn6E"
          },
          "output": {
            "nodeId": "SJNz7nZ04",
            "pinKey": "SJQvVvZC4"
          }
        },
        "r1tcia_Tv": {
          "id": "r1tcia_Tv",
          "input": {
            "nodeId": "HJ6QSnbA4",
            "pinKey": "__in__"
          },
          "output": {
            "nodeId": "Byv5j6OTP",
            "pinKey": "HJSAd3qp4"
          }
        },
        "rJZ5H2-0V": {
          "id": "rJZ5H2-0V",
          "input": {
            "nodeId": "BJNaXh-04",
            "pinKey": "rJeSzevh6E"
          },
          "output": {
            "nodeId": "H1gp8HhZCN",
            "pinKey": "__out__"
          }
        },
        "rJujscPpP": {
          "id": "rJujscPpP",
          "input": {
            "nodeId": "SyQoscDaD",
            "pinKey": "HkXK-dGob"
          },
          "output": {
            "nodeId": "HJHqsqPpw",
            "pinKey": "B1uL9N36V"
          }
        },
        "rk15H3bCV": {
          "id": "rk15H3bCV",
          "input": {
            "nodeId": "BkuT72-C4",
            "pinKey": "rylzxrv2pN"
          },
          "output": {
            "nodeId": "SkpIHnZCE",
            "pinKey": "__out__"
          }
        },
        "ryDRiqwTv": {
          "id": "ryDRiqwTv",
          "input": {
            "nodeId": "S1GCicwpv",
            "pinKey": "HkXK-dGob"
          },
          "output": {
            "nodeId": "rkVJscw6w",
            "pinKey": "HkaK6H-TP"
          }
        },
        "ryEy2qwpD": {
          "id": "ryEy2qwpD",
          "input": {
            "nodeId": "SJNz7nZ04",
            "pinKey": "SyjD72-C4"
          },
          "output": {
            "nodeId": "HJHqsqPpw",
            "pinKey": "HJZ19u42TE"
          }
        }
      },
      "nodes": {
        "BJI2o9w6P": {
          "id": "BJI2o9w6P",
          "position": {
            "x": -17,
            "y": -1,
            "units": "slots"
          },
          "type": "xod/debug/watch"
        },
        "BJNaXh-04": {
          "id": "BJNaXh-04",
          "position": {
            "x": -23,
            "y": -2,
            "units": "slots"
          },
          "type": "@/get-measurement-timing-budget"
        },
        "Bk0IBhb0E": {
          "id": "Bk0IBhb0E",
          "label": "DEV",
          "position": {
            "x": -29,
            "y": -4,
            "units": "slots"
          },
          "type": "xod/patch-nodes/from-bus"
        },
        "BkeyvH2bCE": {
          "id": "BkeyvH2bCE",
          "label": "DEV",
          "position": {
            "x": -23,
            "y": -4,
            "units": "slots"
          },
          "type": "xod/patch-nodes/from-bus"
        },
        "BkuT72-C4": {
          "id": "BkuT72-C4",
          "position": {
            "x": -26,
            "y": -2,
            "units": "slots"
          },
          "type": "@/get-timeout"
        },
        "ByYPE3WRE": {
          "id": "ByYPE3WRE",
          "position": {
            "x": -29,
            "y": -1,
            "units": "slots"
          },
          "size": {
            "height": 1,
            "width": 2,
            "units": "slots"
          },
          "type": "xod/debug/watch"
        },
        "Byv5j6OTP": {
          "boundLiterals": {
            "HyzZSCdpv": "42d"
          },
          "id": "Byv5j6OTP",
          "position": {
            "x": -33,
            "y": -5,
            "units": "slots"
          },
          "type": "@/vl53l1x-device"
        },
        "H12NzhZCV": {
          "boundLiterals": {
            "BkQzsuO2aE": "600",
            "H1GzouO364": "On Boot"
          },
          "id": "H12NzhZCV",
          "position": {
            "x": -29,
            "y": -3,
            "units": "slots"
          },
          "type": "@/set-timeout"
        },
        "H1IN9d-C4": {
          "boundLiterals": {
            "r1TJXObA4": "01h"
          },
          "description": "Patch for testing time-of-flight (ToF) sensor. Run in debug mode.",
          "id": "H1IN9d-C4",
          "position": {
            "x": -23,
            "y": -3,
            "units": "slots"
          },
          "type": "@/set-distance-mode"
        },
        "H1XQs5D6P": {
          "id": "H1XQs5D6P",
          "label": "DEV",
          "position": {
            "x": -20,
            "y": -4,
            "units": "slots"
          },
          "type": "xod/patch-nodes/from-bus"
        },
        "H1eDrnWAV": {
          "id": "H1eDrnWAV",
          "label": "DEV",
          "position": {
            "x": -26,
            "y": -4,
            "units": "slots"
          },
          "type": "xod/patch-nodes/from-bus"
        },
        "H1gp8HhZCN": {
          "id": "H1gp8HhZCN",
          "label": "DEV",
          "position": {
            "x": -24,
            "y": -2,
            "units": "slots"
          },
          "type": "xod/patch-nodes/from-bus"
        },
        "HJ6QSnbA4": {
          "id": "HJ6QSnbA4",
          "label": "DEV",
          "position": {
            "x": -33,
            "y": -4,
            "units": "slots"
          },
          "type": "xod/patch-nodes/to-bus"
        },
        "HJHqsqPpw": {
          "id": "HJHqsqPpw",
          "position": {
            "x": -32,
            "y": -2,
            "units": "slots"
          },
          "type": "@/get-address"
        },
        "HJhwNnbAN": {
          "id": "HJhwNnbAN",
          "position": {
            "x": -23,
            "y": -1,
            "units": "slots"
          },
          "size": {
            "height": 1,
            "width": 2,
            "units": "slots"
          },
          "type": "xod/debug/watch"
        },
        "HkY4n9DaP": {
          "id": "HkY4n9DaP",
          "label": "DEV",
          "position": {
            "x": -18,
            "y": -2,
            "units": "slots"
          },
          "type": "xod/patch-nodes/from-bus"
        },
        "HysIHhZ04": {
          "id": "HysIHhZ04",
          "label": "DEV",
          "position": {
            "x": -30,
            "y": -2,
            "units": "slots"
          },
          "type": "xod/patch-nodes/from-bus"
        },
        "HyuKtJY6w": {
          "id": "HyuKtJY6w",
          "label": "DEV",
          "position": {
            "x": -32,
            "y": -4,
            "units": "slots"
          },
          "type": "xod/patch-nodes/from-bus"
        },
        "S1GCicwpv": {
          "id": "S1GCicwpv",
          "position": {
            "x": -16,
            "y": -1,
            "units": "slots"
          },
          "type": "xod/debug/watch"
        },
        "SJNz7nZ04": {
          "id": "SJNz7nZ04",
          "position": {
            "x": -29,
            "y": -2,
            "units": "slots"
          },
          "type": "@/timeout-occurred"
        },
        "SkKIHnW04": {
          "id": "SkKIHnW04",
          "label": "DEV",
          "position": {
            "x": -21,
            "y": -2,
            "units": "slots"
          },
          "type": "xod/patch-nodes/from-bus"
        },
        "SkTRG9MAN": {
          "id": "SkTRG9MAN",
          "position": {
            "x": -20,
            "y": -2,
            "units": "slots"
          },
          "type": "@/get-distance-mode"
        },
        "SkpIHnZCE": {
          "id": "SkpIHnZCE",
          "label": "DEV",
          "position": {
            "x": -27,
            "y": -2,
            "units": "slots"
          },
          "type": "xod/patch-nodes/from-bus"
        },
        "Sy2zj5Pav": {
          "boundLiterals": {
            "Hk3GIlbTw": "4",
            "Sy-ZUx-6w": "4"
          },
          "id": "Sy2zj5Pav",
          "position": {
            "x": -20,
            "y": -3,
            "units": "slots"
          },
          "type": "@/set-roi"
        },
        "SyQoscDaD": {
          "id": "SyQoscDaD",
          "position": {
            "x": -32,
            "y": -1,
            "units": "slots"
          },
          "size": {
            "height": 1,
            "width": 2,
            "units": "slots"
          },
          "type": "xod/debug/watch"
        },
        "r1s5G3-A4": {
          "boundLiterals": {
            "SJcTJOnTV": "100000"
          },
          "id": "r1s5G3-A4",
          "position": {
            "x": -26,
            "y": -3,
            "units": "slots"
          },
          "type": "@/set-measurement-timing-budget"
        },
        "r1uU4nbCN": {
          "id": "r1uU4nbCN",
          "position": {
            "x": -20,
            "y": -1,
            "units": "slots"
          },
          "size": {
            "height": 1,
            "width": 2,
            "units": "slots"
          },
          "type": "xod/debug/watch"
        },
        "rJquYkYpD": {
          "id": "rJquYkYpD",
          "position": {
            "x": -32,
            "y": -3,
            "units": "slots"
          },
          "type": "@/init"
        },
        "rJqv4hbCE": {
          "id": "rJqv4hbCE",
          "position": {
            "x": -26,
            "y": -1,
            "units": "slots"
          },
          "size": {
            "height": 1,
            "width": 2,
            "units": "slots"
          },
          "type": "xod/debug/watch"
        },
        "rkVJscw6w": {
          "id": "rkVJscw6w",
          "position": {
            "x": -17,
            "y": -2,
            "units": "slots"
          },
          "type": "@/get-roi"
        },
        "ryK5i5DTP": {
          "id": "ryK5i5DTP",
          "label": "DEV",
          "position": {
            "x": -33,
            "y": -2,
            "units": "slots"
          },
          "type": "xod/patch-nodes/from-bus"
        }
      },
      "path": "@/example-test-configuration"
    },
    "@/example-test-tof-sensor": {
      "description": "Patch to test tof-sensor.",
      "links": {
        "Hy75DFbRE": {
          "id": "Hy75DFbRE",
          "input": {
            "nodeId": "S1UFyu-04",
            "pinKey": "H1kEDPWCN"
          },
          "output": {
            "nodeId": "Hy6Kwt-0E",
            "pinKey": "HJU8CE2lW"
          }
        },
        "HyN31db0E": {
          "id": "HyN31db0E",
          "input": {
            "nodeId": "Hyys1d-C4",
            "pinKey": "HkXK-dGob"
          },
          "output": {
            "nodeId": "S1UFyu-04",
            "pinKey": "ByIZfnw-RV"
          }
        },
        "HyeA1O-AE": {
          "id": "HyeA1O-AE",
          "input": {
            "nodeId": "ByziyOZCV",
            "pinKey": "HkXK-dGob"
          },
          "output": {
            "nodeId": "rJhhJOZRV",
            "pinKey": "r1yhZRd8W"
          }
        },
        "S1-3yubCE": {
          "id": "S1-3yubCE",
          "input": {
            "nodeId": "rkR5JdbCV",
            "pinKey": "HkXK-dGob"
          },
          "output": {
            "nodeId": "S1UFyu-04",
            "pinKey": "rJZM2vW0V"
          }
        },
        "SkpjyOW0N": {
          "id": "SkpjyOW0N",
          "input": {
            "nodeId": "BkecJuZAV",
            "pinKey": "HkXK-dGob"
          },
          "output": {
            "nodeId": "S1UFyu-04",
            "pinKey": "HJYZ2P-RN"
          }
        },
        "rJU6yO-CV": {
          "id": "rJU6yO-CV",
          "input": {
            "nodeId": "rJhhJOZRV",
            "pinKey": "HJAq-A_8-"
          },
          "output": {
            "nodeId": "S1UFyu-04",
            "pinKey": "ByI12D-AE"
          }
        },
        "ryJhJuZ04": {
          "id": "ryJhJuZ04",
          "input": {
            "nodeId": "S139JubAE",
            "pinKey": "HkXK-dGob"
          },
          "output": {
            "nodeId": "S1UFyu-04",
            "pinKey": "BJxMnP-0V"
          }
        }
      },
      "nodes": {
        "BkecJuZAV": {
          "id": "BkecJuZAV",
          "position": {
            "x": 1,
            "y": 3,
            "units": "slots"
          },
          "size": {
            "height": 1,
            "width": 2,
            "units": "slots"
          },
          "type": "xod/debug/watch"
        },
        "ByziyOZCV": {
          "id": "ByziyOZCV",
          "position": {
            "x": 9,
            "y": 4,
            "units": "slots"
          },
          "size": {
            "height": 1,
            "width": 2,
            "units": "slots"
          },
          "type": "xod/debug/watch"
        },
        "Hy6Kwt-0E": {
          "boundLiterals": {
            "B13SCNhl-": "0.25"
          },
          "id": "Hy6Kwt-0E",
          "position": {
            "x": 8,
            "y": 1,
            "units": "slots"
          },
          "type": "xod/core/clock"
        },
        "Hyys1d-C4": {
          "id": "Hyys1d-C4",
          "position": {
            "x": 7,
            "y": 3,
            "units": "slots"
          },
          "size": {
            "height": 1,
            "width": 2,
            "units": "slots"
          },
          "type": "xod/debug/watch"
        },
        "S139JubAE": {
          "id": "S139JubAE",
          "position": {
            "x": 3,
            "y": 3,
            "units": "slots"
          },
          "size": {
            "height": 1,
            "width": 2,
            "units": "slots"
          },
          "type": "xod/debug/watch"
        },
        "S1UFyu-04": {
          "boundLiterals": {
            "HyXnQ_-04": "02h",
            "rJEHaGLRD": "4",
            "BJYBaGUAP": "4"
          },
          "id": "S1UFyu-04",
          "position": {
            "x": 4,
            "y": 2,
            "units": "slots"
          },
          "type": "@/tof-sensor"
        },
        "rJhhJOZRV": {
          "id": "rJhhJOZRV",
          "position": {
            "x": 9,
            "y": 3,
            "units": "slots"
          },
          "type": "xod/core/count"
        },
        "rkR5JdbCV": {
          "id": "rkR5JdbCV",
          "position": {
            "x": 5,
            "y": 3,
            "units": "slots"
          },
          "size": {
            "height": 1,
            "width": 2,
            "units": "slots"
          },
          "type": "xod/debug/watch"
        }
      },
      "path": "@/example-test-tof-sensor"
    },
    "@/get-address": {
      "attachments": [
        {
          "content": "node {\n    void evaluate(Context ctx) {\n        // The node responds only if there is an input pulse\n        if (!isInputDirty<input_UPD>(ctx))\n            return;\n        // Get a pointer to the `VL53L1X` class instance\n        auto sensor = getValue<input_DEV>(ctx);\n        emitValue<output_ADDR>(ctx,sensor->getAddress());\n        emitValue<output_DONE>(ctx,1);\n    }\n}\n",
          "encoding": "utf8",
          "filename": "patch.cpp"
        }
      ],
      "description": "Read the I²C address of the VL53L1X.",
      "nodes": {
        "B1uL9N36V": {
          "description": "I²C address of the VL53L1X.",
          "id": "B1uL9N36V",
          "label": "ADDR",
          "position": {
            "x": 0,
            "y": 2,
            "units": "slots"
          },
          "type": "xod/patch-nodes/output-byte"
        },
        "HJZ19u42TE": {
          "description": "Pulses on read of  I²C address.",
          "id": "HJZ19u42TE",
          "label": "DONE",
          "position": {
            "x": 1,
            "y": 2,
            "units": "slots"
          },
          "type": "xod/patch-nodes/output-pulse"
        },
        "HkGJ5u4np4": {
          "description": "Update. Triggers read of address.",
          "id": "HkGJ5u4np4",
          "label": "UPD",
          "position": {
            "x": 1,
            "y": 0,
            "units": "slots"
          },
          "type": "xod/patch-nodes/input-pulse"
        },
        "Skey5dNnTV": {
          "description": "A VL53L1X device.",
          "id": "Skey5dNnTV",
          "label": "DEV",
          "position": {
            "x": 0,
            "y": 0,
            "units": "slots"
          },
          "type": "@/input-vl53l1x-device"
        },
        "SkkqO42aV": {
          "id": "SkkqO42aV",
          "position": {
            "x": 0,
            "y": 1,
            "units": "slots"
          },
          "type": "xod/patch-nodes/not-implemented-in-xod"
        }
      },
      "path": "@/get-address"
    },
    "@/get-distance-mode": {
      "attachments": [
        {
          "filename": "patch.cpp",
          "encoding": "utf-8",
          "content": "node {\n    void evaluate(Context ctx) {\n        // The node responds only if there is an input pulse\n        if (!isInputDirty<input_UPD>(ctx))\n            return;\n        // Get a pointer to the `VL53L1X` class instance\n        auto sensor = getValue<input_DEV>(ctx);\n\n        VL53L1XMTW::DistanceMode mode = sensor->getDistanceMode();\n        \n        switch (mode)\n        {\n            case VL53L1XMTW::Short:\n                emitValue<output_DM>(ctx,0);\n                break;\n\n            case VL53L1XMTW::Medium:\n                emitValue<output_DM>(ctx,1);\n                break;\n\n            case VL53L1XMTW::Long:\n                emitValue<output_DM>(ctx,2);\n                break;\n\n            default:\n                emitValue<output_DM>(ctx,3);\n        }\n        emitValue<output_DONE>(ctx,1);\n    }\n}\n"
        }
      ],
      "description": "Read current distance mode of VL53L1X.",
      "nodes": {
        "ByWKTVn6V": {
          "id": "ByWKTVn6V",
          "position": {
            "x": 0,
            "y": 1,
            "units": "slots"
          },
          "type": "xod/patch-nodes/not-implemented-in-xod"
        },
        "ByYDjKZAE": {
          "description": "Distance mode:\n00h = short;\n01h = medium;\n02h = long;\n03h = unknown.",
          "id": "ByYDjKZAE",
          "label": "DM",
          "position": {
            "x": 0,
            "y": 2,
            "units": "slots"
          },
          "type": "xod/patch-nodes/output-byte"
        },
        "HJZbKp4h6E": {
          "description": "Pulse on read of distance mode.",
          "id": "HJZbKp4h6E",
          "label": "DONE",
          "position": {
            "x": 1,
            "y": 2,
            "units": "slots"
          },
          "type": "xod/patch-nodes/output-pulse"
        },
        "S1e-F6VnTN": {
          "description": "A VL53L1X device.",
          "id": "S1e-F6VnTN",
          "label": "DEV",
          "position": {
            "x": 0,
            "y": 0,
            "units": "slots"
          },
          "type": "@/input-vl53l1x-device"
        },
        "SJzbFT436V": {
          "description": "Update. Triggers read of distance mode.",
          "id": "SJzbFT436V",
          "label": "UPD",
          "position": {
            "x": 1,
            "y": 0,
            "units": "slots"
          },
          "type": "xod/patch-nodes/input-pulse"
        }
      },
      "path": "@/get-distance-mode"
    },
    "@/get-measurement-timing-budget": {
      "attachments": [
        {
          "content": "node {\n    void evaluate(Context ctx) {\n        // The node responds only if there is an input pulse\n        if (!isInputDirty<input_UPD>(ctx))\n            return;\n\n        // Get a pointer to the `VL53L1X` class instance\n        auto sensor = getValue<input_DEV>(ctx);\n\n        emitValue<output_MTB>(ctx,sensor->getMeasurementTimingBudget());\n        emitValue<output_DONE>(ctx,1);\n    }\n}\n",
          "encoding": "utf8",
          "filename": "patch.cpp"
        }
      ],
      "description": "Read measurement timing budget of VL53L1X.",
      "nodes": {
        "Hyrzev2p4": {
          "id": "Hyrzev2p4",
          "position": {
            "x": 0,
            "y": 1,
            "units": "slots"
          },
          "type": "xod/patch-nodes/not-implemented-in-xod"
        },
        "Sya7xwnpE": {
          "description": "Measurement timing budget (microseconds).",
          "id": "Sya7xwnpE",
          "label": "MTB",
          "position": {
            "x": 0,
            "y": 2,
            "units": "slots"
          },
          "type": "xod/patch-nodes/output-number"
        },
        "r1-HGlwnpN": {
          "description": "Pulse on read of measurement timing budget.",
          "id": "r1-HGlwnpN",
          "label": "DONE",
          "position": {
            "x": 1,
            "y": 2,
            "units": "slots"
          },
          "type": "xod/patch-nodes/output-pulse"
        },
        "rJeSzevh6E": {
          "description": "A VL53L1X device.",
          "id": "rJeSzevh6E",
          "label": "DEV",
          "position": {
            "x": 0,
            "y": 0,
            "units": "slots"
          },
          "type": "@/input-vl53l1x-device"
        },
        "rkGHGlD3aE": {
          "description": "Update. Triggers read of measurement timing budget.",
          "id": "rkGHGlD3aE",
          "label": "UPD",
          "position": {
            "x": 1,
            "y": 0,
            "units": "slots"
          },
          "type": "xod/patch-nodes/input-pulse"
        }
      },
      "path": "@/get-measurement-timing-budget"
    },
    "@/get-roi": {
      "attachments": [
        {
          "content": "\nnode {\n    void evaluate(Context ctx) {\n        // The node responds only if there is an input pulse\n        if (!isInputDirty<input_UPD>(ctx))\n            return;\n        // Get a pointer to the `VL53L1X` class instance\n        auto sensor = getValue<input_DEV>(ctx);\n\n        uint16_t x, y;\n        sensor->getROIxy(&x, &y);\n        emitValue<output_X>(ctx, x);\n        emitValue<output_Y>(ctx, y);\n        emitValue<output_DONE>(ctx,1);\n    }\n}\n",
          "encoding": "utf8",
          "filename": "patch.cpp"
        }
      ],
      "description": "Read dimensions of region of interest (ROI).",
      "nodes": {
        "H10vprb6w": {
          "description": "Width of ROI in single photon avalanche detectors (SPADs).",
          "id": "H10vprb6w",
          "label": "X",
          "position": {
            "x": 0,
            "y": 2,
            "units": "slots"
          },
          "type": "xod/patch-nodes/output-number"
        },
        "HJWkarWaP": {
          "description": "A VL53L1X device.",
          "id": "HJWkarWaP",
          "label": "DEV",
          "position": {
            "x": 0,
            "y": 0,
            "units": "slots"
          },
          "type": "@/input-vl53l1x-device"
        },
        "HkaK6H-TP": {
          "description": "Height of ROI in single photon avalanche detectors (SPADs).",
          "id": "HkaK6H-TP",
          "label": "Y",
          "position": {
            "x": 1,
            "y": 2,
            "units": "slots"
          },
          "type": "xod/patch-nodes/output-number"
        },
        "SJuWCS-av": {
          "description": "Pulse when dimensions of ROI have been read.",
          "id": "SJuWCS-av",
          "label": "DONE",
          "position": {
            "x": 2,
            "y": 2,
            "units": "slots"
          },
          "type": "xod/patch-nodes/output-pulse"
        },
        "Sycl6rbaD": {
          "description": "Update. Trigger read of ROI dimensions.",
          "id": "Sycl6rbaD",
          "label": "UPD",
          "position": {
            "x": 1,
            "y": 0,
            "units": "slots"
          },
          "type": "xod/patch-nodes/input-pulse"
        },
        "r1tA3B-aw": {
          "id": "r1tA3B-aw",
          "position": {
            "x": 0,
            "y": 1,
            "units": "slots"
          },
          "type": "xod/patch-nodes/not-implemented-in-xod"
        }
      },
      "path": "@/get-roi"
    },
    "@/get-timeout": {
      "attachments": [
        {
          "content": "node {\n    void evaluate(Context ctx) {\n        // The node responds only if there is an input pulse\n        if (!isInputDirty<input_UPD>(ctx))\n            return;\n\n        // Get a pointer to the `VL53L1X` class instance\n        auto sensor = getValue<input_DEV>(ctx);\n\n        emitValue<output_TO>(ctx,sensor->getTimeout());\n        emitValue<output_DONE>(ctx,1);\n    }\n}\n",
          "encoding": "utf8",
          "filename": "patch.cpp"
        }
      ],
      "description": "Read current timeout setting of VL53L1X.",
      "nodes": {
        "HkzfgBDn6E": {
          "description": "Update. Triggers read of current timeout.",
          "id": "HkzfgBDn6E",
          "label": "UPD",
          "position": {
            "x": 1,
            "y": -0.25,
            "units": "slots"
          },
          "type": "xod/patch-nodes/input-pulse"
        },
        "r1QfgrPhTN": {
          "description": "Timeout (microseconds).",
          "id": "r1QfgrPhTN",
          "label": "TO",
          "position": {
            "x": 0,
            "y": 1.75,
            "units": "slots"
          },
          "type": "xod/patch-nodes/output-number"
        },
        "rk-zgBD3pV": {
          "description": "Pulse on read of timeout.",
          "id": "rk-zgBD3pV",
          "label": "DONE",
          "position": {
            "x": 1,
            "y": 1.75,
            "units": "slots"
          },
          "type": "xod/patch-nodes/output-pulse"
        },
        "rkMlBPnpV": {
          "id": "rkMlBPnpV",
          "position": {
            "x": 0,
            "y": 0.75,
            "units": "slots"
          },
          "type": "xod/patch-nodes/not-implemented-in-xod"
        },
        "rylzxrv2pN": {
          "description": "A VL53L1X device.",
          "id": "rylzxrv2pN",
          "label": "DEV",
          "position": {
            "x": 0,
            "y": -0.25,
            "units": "slots"
          },
          "type": "@/input-vl53l1x-device"
        }
      },
      "path": "@/get-timeout"
    },
    "@/init": {
      "attachments": [
        {
          "content": "node {\n    void evaluate(Context ctx) {\n        // The node responds only if there is an input pulsei\n        if (!isInputDirty<input_INIT>(ctx))\n            return;\n\n        Wire.begin();\n        Wire.setClock(400000); // use 400 kHz I2C\n\n        // Get a pointer to the `VL53L1X` class instance\n        auto sensor = getValue<input_DEV>(ctx);\n\n        sensor->setTimeout(getValue<input_TO>(ctx));\n\n        // Attempt to initialize VL53L1X module; if attempt fails emit error\n        if (!sensor->init()) {\n            raiseError(ctx);\n            return;\n        }\n\n        // Pulse that module initialized successfully\n        emitValue<output_OK>(ctx, 1);\n    }\n}\n",
          "encoding": "utf8",
          "filename": "patch.cpp"
        }
      ],
      "description": "Initialize VL53L1X device.",
      "nodes": {
        "B1VRNa9aN": {
          "boundLiterals": {
            "__out__": "500"
          },
          "description": "Timeout (microseconds).",
          "id": "B1VRNa9aN",
          "label": "TO",
          "position": {
            "x": 1,
            "y": 0,
            "units": "slots"
          },
          "type": "xod/patch-nodes/input-number"
        },
        "ByCrfT5TE": {
          "description": "A VL53L1X device.",
          "id": "ByCrfT5TE",
          "label": "DEV",
          "position": {
            "x": 0,
            "y": 0,
            "units": "slots"
          },
          "type": "@/input-vl53l1x-device"
        },
        "HkOwz69p4": {
          "boundLiterals": {
            "__out__": "On Boot"
          },
          "description": "Trigger for initialization. Default is to initialize on boot.",
          "id": "HkOwz69p4",
          "label": "INIT",
          "position": {
            "x": 2,
            "y": 0,
            "units": "slots"
          },
          "type": "xod/patch-nodes/input-pulse"
        },
        "S1qOGp9aN": {
          "description": "Pulse if initialization successful.",
          "id": "S1qOGp9aN",
          "label": "OK",
          "position": {
            "x": 0,
            "y": 2,
            "units": "slots"
          },
          "type": "xod/patch-nodes/output-pulse"
        },
        "rJ14zTcpN": {
          "id": "rJ14zTcpN",
          "position": {
            "x": 0,
            "y": 1,
            "units": "slots"
          },
          "type": "xod/patch-nodes/not-implemented-in-xod"
        }
      },
      "path": "@/init"
    },
    "@/read-distance": {
      "attachments": [
        {
          "content": "\nnode {\n    void evaluate(Context ctx) {\n        // The node responds only if there is an input pulse\n        if (!isInputDirty<input_UPD>(ctx))\n            return;\n\n        // Get a pointer to the `VL53L1X` class instance\n        auto sensor = getValue<input_DEV>(ctx);\n        sensor->read();\n\n        emitValue<output_RNG>(ctx,sensor->ranging_data.range_mm);\n        emitValue<output_PSCR>(ctx,sensor->ranging_data.peak_signal_count_rate_MCPS);\n        emitValue<output_ACR>(ctx,sensor->ranging_data.ambient_count_rate_MCPS);\n        emitValue<output_STAT>(ctx,sensor->ranging_data.range_status);\n        emitValue<output_DONE>(ctx,1);\n    }\n\n}\n\n",
          "encoding": "utf8",
          "filename": "patch.cpp"
        }
      ],
      "description": "Read distance (mm).",
      "nodes": {
        "B1a1SK26N": {
          "description": "Peak signal count rate (mega-counts per second).",
          "id": "B1a1SK26N",
          "label": "PSCR",
          "position": {
            "x": 1,
            "y": 2,
            "units": "slots"
          },
          "type": "xod/patch-nodes/output-number"
        },
        "B1iPHK26N": {
          "description": "Pulse on read.",
          "id": "B1iPHK26N",
          "label": "DONE",
          "position": {
            "x": 4,
            "y": 2,
            "units": "slots"
          },
          "type": "xod/patch-nodes/output-pulse"
        },
        "BkcMGFn6V": {
          "description": "A VL53L1X device.",
          "id": "BkcMGFn6V",
          "label": "DEV",
          "position": {
            "x": 0,
            "y": 0,
            "units": "slots"
          },
          "type": "@/input-vl53l1x-device"
        },
        "HyY7zF3TN": {
          "description": "Update. Triggers read.",
          "id": "HyY7zF3TN",
          "label": "UPD",
          "position": {
            "x": 1,
            "y": 0,
            "units": "slots"
          },
          "type": "xod/patch-nodes/input-pulse"
        },
        "Hy_rftn6V": {
          "description": "Range in millimetres.",
          "id": "Hy_rftn6V",
          "label": "RNG",
          "position": {
            "x": 0,
            "y": 2,
            "units": "slots"
          },
          "type": "xod/patch-nodes/output-number"
        },
        "SJQf6iCTE": {
          "description": "Status of range measurement:\n0 = range valid;\n1 = standard deviation of measurement is above the internal defined threshold;\n2 = signal value is below the internal defined threshold;\n3 = target is below minimum detection threshold;\n4 = nothing detected in range - try a longer distance mode if applicable;\n5 = hardware failure;\n6 = the range is valid, but the wraparound check has not been done;\n7 = wrapped target, not matching phases;\n9 = crosstalk signal failure;\n10 = synchronization interrupt;\n13 = target is below minimum detection threshold;\n255 = no update.",
          "id": "SJQf6iCTE",
          "label": "STAT",
          "position": {
            "x": 3,
            "y": 2,
            "units": "slots"
          },
          "type": "xod/patch-nodes/output-number"
        },
        "SJrMftnpE": {
          "id": "SJrMftnpE",
          "position": {
            "x": 0,
            "y": 1,
            "units": "slots"
          },
          "type": "xod/patch-nodes/not-implemented-in-xod"
        },
        "ry_BSF2aN": {
          "description": "Ambient count rate (mega-counts per second).",
          "id": "ry_BSF2aN",
          "label": "ACR",
          "position": {
            "x": 2,
            "y": 2,
            "units": "slots"
          },
          "type": "xod/patch-nodes/output-number"
        }
      },
      "path": "@/read-distance"
    },
    "@/set-address": {
      "attachments": [
        {
          "content": "node {\n    void evaluate(Context ctx) {\n        // The node responds only if there is an input pulse\n        if (!isInputDirty<input_UPD>(ctx))\n            return;\n        // Get a pointer to the `VL53L1X` class instance\n        auto sensor = getValue<input_DEV>(ctx);\n        sensor->setAddress(getValue<input_ADDR>(ctx));\n        emitValue<output_DONE>(ctx,1);\n    }\n}\n",
          "encoding": "utf8",
          "filename": "patch.cpp"
        }
      ],
      "description": "Set I²C address of VL53L1X device.",
      "nodes": {
        "BydbeeW6D": {
          "description": "Pulse when address set.",
          "id": "BydbeeW6D",
          "label": "DONE",
          "position": {
            "x": 0,
            "y": 2,
            "units": "slots"
          },
          "type": "xod/patch-nodes/output-pulse"
        },
        "HJAnkxbTP": {
          "id": "HJAnkxbTP",
          "position": {
            "x": 0,
            "y": 1,
            "units": "slots"
          },
          "type": "xod/patch-nodes/not-implemented-in-xod"
        },
        "S1RHxeWTP": {
          "description": "A VL53L1X device.",
          "id": "S1RHxeWTP",
          "label": "DEV",
          "position": {
            "x": 0,
            "y": 0,
            "units": "slots"
          },
          "type": "@/input-vl53l1x-device"
        },
        "r1sAygZ6v": {
          "description": "Update. Trigger for setting address.",
          "id": "r1sAygZ6v",
          "label": "UPD",
          "position": {
            "x": 2,
            "y": 0,
            "units": "slots"
          },
          "type": "xod/patch-nodes/input-pulse"
        },
        "rkazegW6w": {
          "boundLiterals": {
            "__out__": "29h"
          },
          "description": "I²C address.",
          "id": "rkazegW6w",
          "label": "ADDR",
          "position": {
            "x": 1,
            "y": 0,
            "units": "slots"
          },
          "type": "xod/patch-nodes/input-byte"
        }
      },
      "path": "@/set-address"
    },
    "@/set-distance-mode": {
      "attachments": [
        {
          "filename": "patch.cpp",
          "encoding": "utf-8",
          "content": "node {\n    void evaluate(Context ctx) {\n        // The node responds only if there is an input pulse\n        if (!isInputDirty<input_UPD>(ctx))\n            return;\n\n        // Get a pointer to the `VL53L1X` class instance\n        auto sensor = getValue<input_DEV>(ctx);\n        // get distance mode\n        auto mode = getValue<input_DM>(ctx);\n\n        if(mode==0)\n        {\n            if(!sensor->setDistanceMode(VL53L1XMTW::Short)) {\n                raiseError(ctx);\n                return;\n            }\n        }\n\n        if(mode==1)\n        {\n            if(!sensor->setDistanceMode(VL53L1XMTW::Medium)) {\n                raiseError(ctx);\n                return;\n            }\n        }\n\n        if(mode==2)\n        {\n            if(!sensor->setDistanceMode(VL53L1XMTW::Long)) {\n                raiseError(ctx);\n                return;\n            }\n        }\n        emitValue<output_OK>(ctx,1);\n    }\n}\n\n\n\n"
        }
      ],
      "description": "Set distance mode. The VL53L1X has three distance modes (DM): short, medium, and long.\nLong distance mode allows the longest possible ranging distance of 4 m to be reached. However, this maximum ranging distance is impacted by ambient light.\nShort distance mode is more immune to ambient light, but its maximum ranging distance is typically limited to 1.3 m.",
      "nodes": {
        "BkGM8aBhaE": {
          "description": "Update. Trigger for setting distance mode.",
          "id": "BkGM8aBhaE",
          "label": "UPD",
          "position": {
            "x": 2,
            "y": 0,
            "units": "slots"
          },
          "type": "xod/patch-nodes/input-pulse"
        },
        "HkWzLaShaE": {
          "description": "Pulses when distance mode is set.",
          "id": "HkWzLaShaE",
          "label": "OK",
          "position": {
            "x": 0,
            "y": 2,
            "units": "slots"
          },
          "type": "xod/patch-nodes/output-pulse"
        },
        "HyzITH3aN": {
          "id": "HyzITH3aN",
          "position": {
            "x": 0,
            "y": 1,
            "units": "slots"
          },
          "type": "xod/patch-nodes/not-implemented-in-xod"
        },
        "r1TJXObA4": {
          "boundLiterals": {
            "__out__": "02h"
          },
          "description": "Distance mode:\n00h = short;\n01h = medium;\n02h = long.",
          "id": "r1TJXObA4",
          "label": "DM",
          "position": {
            "x": 1,
            "y": 0,
            "units": "slots"
          },
          "type": "xod/patch-nodes/input-byte"
        },
        "r1ezU6rhTV": {
          "description": "A VL53L1X device.",
          "id": "r1ezU6rhTV",
          "label": "DEV",
          "position": {
            "x": 0,
            "y": 0,
            "units": "slots"
          },
          "type": "@/input-vl53l1x-device"
        }
      },
      "path": "@/set-distance-mode"
    },
    "@/set-measurement-timing-budget": {
      "attachments": [
        {
          "content": "\nstruct State {\n};\n\n{{ GENERATED_CODE }}\n\nvoid evaluate(Context ctx) {\n    // The node responds only if there is an input pulse\n    if (!isInputDirty<input_UPD>(ctx))\n        return;\n\n    // Get a pointer to the `VL53L1X` class instance\n    auto sensor = getValue<input_DEV>(ctx);\n\n    // Attempt to set measurement timing budget; if attempt fails emit pulse from error port\n    if (!sensor->setMeasurementTimingBudget(getValue<input_MTB>(ctx))) {\n        raiseError(ctx);\n        return;\n    }\n\n    emitValue<output_OK>(ctx,1);\n}\n",
          "encoding": "utf8",
          "filename": "patch.cpp"
        }
      ],
      "description": "Set measurement timing budget. The VL53L1X timing budget can be set from 20 ms up to 1000 ms.\n• 20 ms is the minimum timing budget and can be used only in Short distance mode.\n• 33 ms is the minimum timing budget which can work for all distance modes.\n• 140 ms is the timing budget which allows the maximum distance of 4 m (in the dark on a white chart) to be reached under Long distance mode\nIncreasing the timing budget increases the maximum distance the device can range and improves the repeatability error. However, average power consumption augments accordingly.",
      "nodes": {
        "B1Mb4CwnaV": {
          "description": "Update. Trigger for setting measurement timing budget.",
          "id": "B1Mb4CwnaV",
          "label": "UPD",
          "position": {
            "x": 2,
            "y": 0,
            "units": "slots"
          },
          "type": "xod/patch-nodes/input-pulse"
        },
        "Hk-NRD2TE": {
          "id": "Hk-NRD2TE",
          "position": {
            "x": 0,
            "y": 1,
            "units": "slots"
          },
          "type": "xod/patch-nodes/not-implemented-in-xod"
        },
        "SJcTJOnTV": {
          "boundLiterals": {
            "__out__": "200000"
          },
          "description": "Measurement timing budget (microseconds). N.B. units are microseconds not milliseconds.",
          "id": "SJcTJOnTV",
          "label": "MTB",
          "position": {
            "x": 1,
            "y": 0,
            "units": "slots"
          },
          "type": "xod/patch-nodes/input-number"
        },
        "SygbNCw2TN": {
          "description": "A VL53L1X device.",
          "id": "SygbNCw2TN",
          "label": "DEV",
          "position": {
            "x": 0,
            "y": 0,
            "units": "slots"
          },
          "type": "@/input-vl53l1x-device"
        },
        "r1ZbNRPn6V": {
          "description": "Pulses when measurement timing budget is set.",
          "id": "r1ZbNRPn6V",
          "label": "OK",
          "position": {
            "x": 0,
            "y": 2,
            "units": "slots"
          },
          "type": "xod/patch-nodes/output-pulse"
        }
      },
      "path": "@/set-measurement-timing-budget"
    },
    "@/set-roi": {
      "attachments": [
        {
          "content": "\nnode {\n\n    void evaluate(Context ctx) {\n        // The node responds only if there is an input pulse\n        if (!isInputDirty<input_UPD>(ctx))\n            return;\n        // Get a pointer to the `VL53L1X` class instance\n        auto sensor = getValue<input_DEV>(ctx);\n        sensor->setROI(getValue<input_X>(ctx), getValue<input_Y>(ctx));\n        emitValue<output_DONE>(ctx,1);\n    }\n}\n",
          "encoding": "utf8",
          "filename": "patch.cpp"
        }
      ],
      "description": "Set a region of interest (ROI). The ROI position is centered, only the ROI size can be changed. The full sensor (16x16 SPADs) provides a nominal\n27 ° field of view (FoV). The FoV can be reduced to a minimum of 15 ° by setting the ROI to 4x4 SPADs. For further information please see: https://www.st.com/resource/en/application_note/dm00516219-using-the-programmable-region-of-interest-roi-with-the-vl53l1x-stmicroelectronics.pdf",
      "nodes": {
        "Bk4Lo5vaP": {
          "description": "Update. Trigger set ROI.",
          "id": "Bk4Lo5vaP",
          "label": "UPD",
          "position": {
            "x": 3,
            "y": 0,
            "units": "slots"
          },
          "type": "xod/patch-nodes/input-pulse"
        },
        "Hk3GIlbTw": {
          "boundLiterals": {
            "__out__": "4"
          },
          "description": "ROI height in single photon avalanche detectors (SPADs). Full height of sensor is 16 SPADS. Minimum height of ROI is 4 SPADs.",
          "id": "Hk3GIlbTw",
          "label": "Y",
          "position": {
            "x": 2,
            "y": 0,
            "units": "slots"
          },
          "type": "xod/patch-nodes/input-number"
        },
        "HyPX8xbav": {
          "description": "A VL53L1X device.",
          "id": "HyPX8xbav",
          "label": "DEV",
          "position": {
            "x": 0,
            "y": 0,
            "units": "slots"
          },
          "type": "@/input-vl53l1x-device"
        },
        "HyXl8g-aP": {
          "id": "HyXl8g-aP",
          "position": {
            "x": 0,
            "y": 1,
            "units": "slots"
          },
          "type": "xod/patch-nodes/not-implemented-in-xod"
        },
        "SJoNUx-6D": {
          "description": "Pulse when ROI set.",
          "id": "SJoNUx-6D",
          "label": "DONE",
          "position": {
            "x": 0,
            "y": 2,
            "units": "slots"
          },
          "type": "xod/patch-nodes/output-pulse"
        },
        "Sy-ZUx-6w": {
          "boundLiterals": {
            "__out__": "4"
          },
          "description": "ROI width in single photon avalanche detectors (SPADs). Full width of sensor is 16 SPADS. Minimum width of ROI is 4 SPADs.",
          "id": "Sy-ZUx-6w",
          "label": "X",
          "position": {
            "x": 1,
            "y": 0,
            "units": "slots"
          },
          "type": "xod/patch-nodes/input-number"
        }
      },
      "path": "@/set-roi"
    },
    "@/set-timeout": {
      "attachments": [
        {
          "content": "node {\n    void evaluate(Context ctx) {\n        // The node responds only if there is an input pulse\n        if (!isInputDirty<input_UPD>(ctx))\n            return;\n\n        // Get a pointer to the `VL53L1X` class instance\n        auto sensor = getValue<input_DEV>(ctx);\n\n        sensor->setTimeout(getValue<input_TO>(ctx));\n        emitValue<output_DONE>(ctx,1);\n    }\n\n}\n\n\n",
          "encoding": "utf8",
          "filename": "patch.cpp"
        }
      ],
      "description": "Set timeout.",
      "nodes": {
        "BkQzsuO2aE": {
          "boundLiterals": {
            "__out__": "500"
          },
          "description": "Timeout (microseconds).",
          "id": "BkQzsuO2aE",
          "label": "TO",
          "position": {
            "x": 1,
            "y": 0,
            "units": "slots"
          },
          "type": "xod/patch-nodes/input-number"
        },
        "H1GzouO364": {
          "description": "Update. Trigger for setting timeout.",
          "id": "H1GzouO364",
          "label": "UPD",
          "position": {
            "x": 2,
            "y": 0,
            "units": "slots"
          },
          "type": "xod/patch-nodes/input-pulse"
        },
        "H1bGjOu2aN": {
          "description": "Pulses when timeout set.",
          "id": "H1bGjOu2aN",
          "label": "DONE",
          "position": {
            "x": 0,
            "y": 2,
            "units": "slots"
          },
          "type": "xod/patch-nodes/output-pulse"
        },
        "H1zjOu3TN": {
          "id": "H1zjOu3TN",
          "position": {
            "x": 0,
            "y": 1,
            "units": "slots"
          },
          "type": "xod/patch-nodes/not-implemented-in-xod"
        },
        "ryeGjO_2TE": {
          "description": "A VL53L1X device.",
          "id": "ryeGjO_2TE",
          "label": "DEV",
          "position": {
            "x": 0,
            "y": 0,
            "units": "slots"
          },
          "type": "@/input-vl53l1x-device"
        }
      },
      "path": "@/set-timeout"
    },
    "@/start-continuous": {
      "attachments": [
        {
          "content": "node {\n    void evaluate(Context ctx) {\n        // The node responds only if there is an input pulse\n        if (!isInputDirty<input_UPD>(ctx))\n            return;\n\n        // Get a pointer to the `VL53L1X` class instance\n        auto sensor = getValue<input_DEV>(ctx);\n\n        sensor->startContinuous(getValue<input_IMP>(ctx));\n\n        emitValue<output_DONE>(ctx,1);\n    }\n\n}\n\n",
          "encoding": "utf8",
          "filename": "patch.cpp"
        }
      ],
      "description": "Start continuous ranging measurements, with the given inter-measurement period in milliseconds determining how often the sensor takes a measurement.",
      "nodes": {
        "B1-qw43pE": {
          "description": "Trigger for starting continuous ranging.",
          "id": "B1-qw43pE",
          "label": "UPD",
          "position": {
            "x": 2,
            "y": 0,
            "units": "slots"
          },
          "type": "xod/patch-nodes/input-pulse"
        },
        "H1qQNEn6N": {
          "id": "H1qQNEn6N",
          "position": {
            "x": 0,
            "y": 1,
            "units": "slots"
          },
          "type": "xod/patch-nodes/not-implemented-in-xod"
        },
        "Hyhr4V2T4": {
          "description": "A VL53L1X device.",
          "id": "Hyhr4V2T4",
          "label": "DEV",
          "position": {
            "x": 0,
            "y": 0,
            "units": "slots"
          },
          "type": "@/input-vl53l1x-device"
        },
        "SJx7BV3TN": {
          "description": "Pulse on start of continuous ranging.",
          "id": "SJx7BV3TN",
          "label": "DONE",
          "position": {
            "x": 0,
            "y": 2,
            "units": "slots"
          },
          "type": "xod/patch-nodes/output-pulse"
        },
        "SknOEV2aN": {
          "boundLiterals": {
            "__out__": "50"
          },
          "description": "Inter-measurement period (milliseconds). This period should be at least as long as the measurement timing budget.",
          "id": "SknOEV2aN",
          "label": "IMP",
          "position": {
            "x": 1,
            "y": 0,
            "units": "slots"
          },
          "type": "xod/patch-nodes/input-number"
        }
      },
      "path": "@/start-continuous"
    },
    "@/stop-continuous": {
      "attachments": [
        {
          "content": "node {\n    void evaluate(Context ctx) {\n        // The node responds only if there is an input pulse\n        if (!isInputDirty<input_UPD>(ctx))\n            return;\n\n        // Get a pointer to the `VL53L1X` class instance\n        auto sensor = getValue<input_DEV>(ctx);\n\n        sensor->stopContinuous();\n\n        emitValue<output_DONE>(ctx,1);\n    }\n\n}\n\n",
          "encoding": "utf8",
          "filename": "patch.cpp"
        }
      ],
      "description": "Stop continuous measurements.",
      "nodes": {
        "ByQuf_E2aV": {
          "description": "Update. Trigger for stopping continuous ranging.",
          "id": "ByQuf_E2aV",
          "label": "UPD",
          "position": {
            "x": 1,
            "y": 0,
            "units": "slots"
          },
          "type": "xod/patch-nodes/input-pulse"
        },
        "HygdzONn6N": {
          "description": "A VL53L1X device.",
          "id": "HygdzONn6N",
          "label": "DEV",
          "position": {
            "x": 0,
            "y": 0,
            "units": "slots"
          },
          "type": "@/input-vl53l1x-device"
        },
        "r1_MdNhaN": {
          "id": "r1_MdNhaN",
          "position": {
            "x": 0,
            "y": 1,
            "units": "slots"
          },
          "type": "xod/patch-nodes/not-implemented-in-xod"
        },
        "ryfOMOVh6V": {
          "description": "Pulse when continuous ranging stopped.",
          "id": "ryfOMOVh6V",
          "label": "DONE",
          "position": {
            "x": 0,
            "y": 2,
            "units": "slots"
          },
          "type": "xod/patch-nodes/output-pulse"
        }
      },
      "path": "@/stop-continuous"
    },
    "@/timeout-occurred": {
      "attachments": [
        {
          "content": "node {\n    void evaluate(Context ctx) {\n        // The node responds only if there is an input pulse\n        if (!isInputDirty<input_UPD>(ctx))\n            return;\n\n        // Get a pointer to the `VL53L1X` class instance\n        auto sensor = getValue<input_DEV>(ctx);\n\n        emitValue<output_TO>(ctx,sensor->timeoutOccurred());\n        emitValue<output_DONE>(ctx,1);\n\n    }\n\n}\n\n",
          "encoding": "utf8",
          "filename": "patch.cpp"
        }
      ],
      "description": "Did a timeout occur in one of the read functions since the last call to this node?",
      "nodes": {
        "S1UbNwb04": {
          "description": "Timeout occurred.",
          "id": "S1UbNwb04",
          "label": "TO",
          "position": {
            "x": -18,
            "y": -2,
            "units": "slots"
          },
          "type": "xod/patch-nodes/output-boolean"
        },
        "SJIVEP-R4": {
          "description": "A VL53L1X device.",
          "id": "SJIVEP-R4",
          "label": "DEV",
          "position": {
            "x": -18,
            "y": -4,
            "units": "slots"
          },
          "type": "@/input-vl53l1x-device"
        },
        "SJQvVvZC4": {
          "description": "Pulse on check for timeout.",
          "id": "SJQvVvZC4",
          "label": "DONE",
          "position": {
            "x": -17,
            "y": -2,
            "units": "slots"
          },
          "type": "xod/patch-nodes/output-pulse"
        },
        "SyDaQD-R4": {
          "id": "SyDaQD-R4",
          "position": {
            "x": -18,
            "y": -3,
            "units": "slots"
          },
          "type": "xod/patch-nodes/not-implemented-in-xod"
        },
        "SyjD72-C4": {
          "description": "Update. Trigger check if timeout occurred.",
          "id": "SyjD72-C4",
          "label": "UPD",
          "position": {
            "x": -17,
            "y": -4,
            "units": "slots"
          },
          "type": "xod/patch-nodes/input-pulse"
        }
      },
      "path": "@/timeout-occurred"
    },
    "@/tof-sensor": {
      "description": "Time-of-Flight (ToF) sensor.",
      "links": {
        "BkY8hPW0N": {
          "id": "BkY8hPW0N",
          "input": {
            "nodeId": "rJZM2vW0V",
            "pinKey": "__in__"
          },
          "output": {
            "nodeId": "BkzxlchaV",
            "pinKey": "ry_BSF2aN"
          }
        },
        "BkZo2e9hpE": {
          "id": "BkZo2e9hpE",
          "input": {
            "nodeId": "B1gjhlq3TN",
            "pinKey": "__in__"
          },
          "output": {
            "nodeId": "SJs2ec36V",
            "pinKey": "HkyxURuSPyW"
          }
        },
        "Bkwi3kKav": {
          "id": "Bkwi3kKav",
          "input": {
            "nodeId": "H1aSnkt6D",
            "pinKey": "B1VRNa9aN"
          },
          "output": {
            "nodeId": "Bk35cP-RE",
            "pinKey": "__out__"
          }
        },
        "ByW6Fw-0N": {
          "id": "ByW6Fw-0N",
          "input": {
            "nodeId": "SJs2ec36V",
            "pinKey": "Bkh8A_Sv1-"
          },
          "output": {
            "nodeId": "rJ03FDbCN",
            "pinKey": "SJx7BV3TN"
          }
        },
        "H1BsuDZAV": {
          "id": "H1BsuDZAV",
          "input": {
            "nodeId": "HkVKvP-A4",
            "pinKey": "r1ezU6rhTV"
          },
          "output": {
            "nodeId": "rJ6Fuw-A4",
            "pinKey": "__out__"
          }
        },
        "Hk7uOPZ0E": {
          "id": "Hk7uOPZ0E",
          "input": {
            "nodeId": "BkzxlchaV",
            "pinKey": "BkcMGFn6V"
          },
          "output": {
            "nodeId": "HyCDdvbCN",
            "pinKey": "__out__"
          }
        },
        "HkhTKDb0E": {
          "id": "HkhTKDb0E",
          "input": {
            "nodeId": "rktpKPZRN",
            "pinKey": "SygbNCw2TN"
          },
          "output": {
            "nodeId": "SJ_tdDbAE",
            "pinKey": "__out__"
          }
        },
        "S1cI3PZ0E": {
          "id": "S1cI3PZ0E",
          "input": {
            "nodeId": "ByIZfnw-RV",
            "pinKey": "__in__"
          },
          "output": {
            "nodeId": "BkzxlchaV",
            "pinKey": "SJQf6iCTE"
          }
        },
        "SJS82DZ0N": {
          "id": "SJS82DZ0N",
          "input": {
            "nodeId": "HJYZ2P-RN",
            "pinKey": "__in__"
          },
          "output": {
            "nodeId": "BkzxlchaV",
            "pinKey": "Hy_rftn6V"
          }
        },
        "SJXWhvZAN": {
          "id": "SJXWhvZAN",
          "input": {
            "nodeId": "ByI12D-AE",
            "pinKey": "__in__"
          },
          "output": {
            "nodeId": "BkzxlchaV",
            "pinKey": "B1iPHK26N"
          }
        },
        "SkD0x92pN": {
          "id": "SkD0x92pN",
          "input": {
            "nodeId": "BkzxlchaV",
            "pinKey": "HyY7zF3TN"
          },
          "output": {
            "nodeId": "SkeRe9hpN",
            "pinKey": "OkPg7GDaW"
          }
        },
        "Sknb9D-RE": {
          "id": "Sknb9D-RE",
          "input": {
            "nodeId": "HkVKvP-A4",
            "pinKey": "BkGM8aBhaE"
          },
          "output": {
            "nodeId": "rktpKPZRN",
            "pinKey": "r1ZbNRPn6V"
          }
        },
        "SyrJsDWRE": {
          "id": "SyrJsDWRE",
          "input": {
            "nodeId": "rktpKPZRN",
            "pinKey": "SJcTJOnTV"
          },
          "output": {
            "nodeId": "B1icqP-0V",
            "pinKey": "__out__"
          }
        },
        "r1Nx0l536N": {
          "id": "r1Nx0l536N",
          "input": {
            "nodeId": "SkeRe9hpN",
            "pinKey": "B1P1nFwaM"
          },
          "output": {
            "nodeId": "HkMx0lc2aV",
            "pinKey": "__out__"
          }
        },
        "r1VNvPb0E": {
          "id": "r1VNvPb0E",
          "input": {
            "nodeId": "SkeRe9hpN",
            "pinKey": "SJ-1mZPTz"
          },
          "output": {
            "nodeId": "H1kEDPWCN",
            "pinKey": "__out__"
          }
        },
        "rJOvuP-RN": {
          "id": "rJOvuP-RN",
          "input": {
            "nodeId": "SkYL_D-CV",
            "pinKey": "__in__"
          },
          "output": {
            "nodeId": "ryn6y936N",
            "pinKey": "HJSAd3qp4"
          }
        },
        "rJeatPb04": {
          "id": "rJeatPb04",
          "input": {
            "nodeId": "rJ03FDbCN",
            "pinKey": "Hyhr4V2T4"
          },
          "output": {
            "nodeId": "S1G5OvZRN",
            "pinKey": "__out__"
          }
        },
        "rJxAFP-AN": {
          "id": "rJxAFP-AN",
          "input": {
            "nodeId": "rJ03FDbCN",
            "pinKey": "B1-qw43pE"
          },
          "output": {
            "nodeId": "HkVKvP-A4",
            "pinKey": "HkWzLaShaE"
          }
        },
        "rkKhmuW0V": {
          "id": "rkKhmuW0V",
          "input": {
            "nodeId": "HkVKvP-A4",
            "pinKey": "r1TJXObA4"
          },
          "output": {
            "nodeId": "HyXnQ_-04",
            "pinKey": "__out__"
          }
        },
        "ryCyiDbRE": {
          "id": "ryCyiDbRE",
          "input": {
            "nodeId": "rJ03FDbCN",
            "pinKey": "SknOEV2aN"
          },
          "output": {
            "nodeId": "HJf9cv-RN",
            "pinKey": "__out__"
          }
        },
        "ryPLhvZC4": {
          "id": "ryPLhvZC4",
          "input": {
            "nodeId": "BJxMnP-0V",
            "pinKey": "__in__"
          },
          "output": {
            "nodeId": "BkzxlchaV",
            "pinKey": "B1a1SK26N"
          }
        },
        "rydp3yK6w": {
          "id": "rydp3yK6w",
          "input": {
            "nodeId": "H1aSnkt6D",
            "pinKey": "ByCrfT5TE"
          },
          "output": {
            "nodeId": "r130Uqv6P",
            "pinKey": "__out__"
          }
        },
        "rJtNpfLAP": {
          "id": "rJtNpfLAP",
          "output": {
            "nodeId": "S1eVaGI0v",
            "pinKey": "__out__"
          },
          "input": {
            "nodeId": "rkGC3MIAw",
            "pinKey": "HyPX8xbav"
          }
        },
        "rk5DpzI0w": {
          "id": "rk5DpzI0w",
          "output": {
            "nodeId": "rJEHaGLRD",
            "pinKey": "__out__"
          },
          "input": {
            "nodeId": "rkGC3MIAw",
            "pinKey": "Sy-ZUx-6w"
          }
        },
        "BJsPpGIRv": {
          "id": "BJsPpGIRv",
          "output": {
            "nodeId": "BJYBaGUAP",
            "pinKey": "__out__"
          },
          "input": {
            "nodeId": "rkGC3MIAw",
            "pinKey": "Hk3GIlbTw"
          }
        },
        "SyTY6zUAP": {
          "id": "SyTY6zUAP",
          "output": {
            "nodeId": "H1aSnkt6D",
            "pinKey": "S1qOGp9aN"
          },
          "input": {
            "nodeId": "rkGC3MIAw",
            "pinKey": "Bk4Lo5vaP"
          }
        },
        "Bk1cpGLCD": {
          "id": "Bk1cpGLCD",
          "output": {
            "nodeId": "rkGC3MIAw",
            "pinKey": "SJoNUx-6D"
          },
          "input": {
            "nodeId": "rktpKPZRN",
            "pinKey": "B1Mb4CwnaV"
          }
        }
      },
      "nodes": {
        "B1gjhlq3TN": {
          "id": "B1gjhlq3TN",
          "label": "INTD",
          "position": {
            "x": -5,
            "y": 6,
            "units": "slots"
          },
          "type": "xod/patch-nodes/to-bus"
        },
        "B1icqP-0V": {
          "boundLiterals": {
            "__out__": "200000"
          },
          "description": "Measurement timing budget (microseconds).",
          "id": "B1icqP-0V",
          "label": "MTB",
          "position": {
            "x": 0,
            "y": 0,
            "units": "slots"
          },
          "type": "xod/patch-nodes/input-number"
        },
        "BJxMnP-0V": {
          "description": "Peak signal count rate (mega-counts per second).",
          "id": "BJxMnP-0V",
          "label": "PSCR",
          "position": {
            "x": 6,
            "y": 4,
            "units": "slots"
          },
          "type": "xod/patch-nodes/output-number"
        },
        "Bk35cP-RE": {
          "boundLiterals": {
            "__out__": "500"
          },
          "description": "Timeout (microseconds).",
          "id": "Bk35cP-RE",
          "label": "TO",
          "position": {
            "x": -6,
            "y": 0,
            "units": "slots"
          },
          "type": "xod/patch-nodes/input-number"
        },
        "BkzxlchaV": {
          "id": "BkzxlchaV",
          "position": {
            "x": 5,
            "y": 3,
            "units": "slots"
          },
          "type": "@/read-distance"
        },
        "ByI12D-AE": {
          "description": "Pulse on read.",
          "id": "ByI12D-AE",
          "label": "OK",
          "position": {
            "x": 9,
            "y": 4,
            "units": "slots"
          },
          "type": "xod/patch-nodes/output-pulse"
        },
        "ByIZfnw-RV": {
          "description": "Status of range measurement:\n0 = range valid;\n1 = standard deviation of measurement is above the internal defined threshold;\n2 = signal value is below the internal defined threshold;\n3 = target is below minimum detection threshold;\n4 = nothing detected in range - try a longer distance mode if applicable;\n5 = hardware failure;\n6 = the range is valid, but the wraparound check has not been done;\n7 = wrapped target, not matching phases;\n9 = crosstalk signal failure;\n10 = synchronization interrupt;\n13 = target is below minimum detection threshold;\n255 = no update.",
          "id": "ByIZfnw-RV",
          "label": "STAT",
          "position": {
            "x": 8,
            "y": 4,
            "units": "slots"
          },
          "type": "xod/patch-nodes/output-number"
        },
        "H1aSnkt6D": {
          "id": "H1aSnkt6D",
          "position": {
            "x": -7,
            "y": 1,
            "units": "slots"
          },
          "type": "@/init"
        },
        "H1kEDPWCN": {
          "description": "Update. Triggers read.",
          "id": "H1kEDPWCN",
          "label": "UPD",
          "position": {
            "x": 6,
            "y": 0,
            "units": "slots"
          },
          "type": "xod/patch-nodes/input-pulse"
        },
        "HJYZ2P-RN": {
          "description": "Range in millimetres.",
          "id": "HJYZ2P-RN",
          "label": "RNG",
          "position": {
            "x": 5,
            "y": 4,
            "units": "slots"
          },
          "type": "xod/patch-nodes/output-number"
        },
        "HJf9cv-RN": {
          "boundLiterals": {
            "__out__": "200"
          },
          "description": "Inter-measurement period (milliseconds). This period should be at least as long as the measurement timing budget.",
          "id": "HJf9cv-RN",
          "label": "IMP",
          "position": {
            "x": -4,
            "y": 0,
            "units": "slots"
          },
          "type": "xod/patch-nodes/input-number"
        },
        "HkMx0lc2aV": {
          "id": "HkMx0lc2aV",
          "label": "INTD",
          "position": {
            "x": 7,
            "y": 1,
            "units": "slots"
          },
          "type": "xod/patch-nodes/from-bus"
        },
        "HkVKvP-A4": {
          "boundLiterals": {
            "r1TJXObA4": "02h"
          },
          "id": "HkVKvP-A4",
          "position": {
            "x": -3,
            "y": 3,
            "units": "slots"
          },
          "type": "@/set-distance-mode"
        },
        "HyCDdvbCN": {
          "id": "HyCDdvbCN",
          "label": "DEV",
          "position": {
            "x": 5,
            "y": 2,
            "units": "slots"
          },
          "type": "xod/patch-nodes/from-bus"
        },
        "HyXnQ_-04": {
          "description": "Distance mode:\n00h = short;\n01h = medium;\n02h = long.",
          "id": "HyXnQ_-04",
          "label": "DM",
          "position": {
            "x": -2,
            "y": 0,
            "units": "slots"
          },
          "type": "xod/patch-nodes/input-byte"
        },
        "S1G5OvZRN": {
          "id": "S1G5OvZRN",
          "label": "DEV",
          "position": {
            "x": -5,
            "y": 3,
            "units": "slots"
          },
          "type": "xod/patch-nodes/from-bus"
        },
        "SJ_tdDbAE": {
          "id": "SJ_tdDbAE",
          "label": "DEV",
          "position": {
            "x": -1,
            "y": 1,
            "units": "slots"
          },
          "type": "xod/patch-nodes/from-bus"
        },
        "SJs2ec36V": {
          "id": "SJs2ec36V",
          "position": {
            "x": -5,
            "y": 5,
            "units": "slots"
          },
          "type": "xod/core/flip-flop"
        },
        "SkYL_D-CV": {
          "id": "SkYL_D-CV",
          "label": "DEV",
          "position": {
            "x": -9,
            "y": 2,
            "units": "slots"
          },
          "type": "xod/patch-nodes/to-bus"
        },
        "SkeRe9hpN": {
          "id": "SkeRe9hpN",
          "position": {
            "x": 6,
            "y": 2,
            "units": "slots"
          },
          "type": "xod/core/gate"
        },
        "r130Uqv6P": {
          "id": "r130Uqv6P",
          "label": "DEV",
          "position": {
            "x": -7,
            "y": 0,
            "units": "slots"
          },
          "type": "xod/patch-nodes/from-bus"
        },
        "rJ03FDbCN": {
          "id": "rJ03FDbCN",
          "position": {
            "x": -5,
            "y": 4,
            "units": "slots"
          },
          "type": "@/start-continuous"
        },
        "rJ6Fuw-A4": {
          "id": "rJ6Fuw-A4",
          "label": "DEV",
          "position": {
            "x": -3,
            "y": 2,
            "units": "slots"
          },
          "type": "xod/patch-nodes/from-bus"
        },
        "rJZM2vW0V": {
          "description": "Ambient count rate (mega-counts per second).",
          "id": "rJZM2vW0V",
          "label": "ACR",
          "position": {
            "x": 7,
            "y": 4,
            "units": "slots"
          },
          "type": "xod/patch-nodes/output-number"
        },
        "rktpKPZRN": {
          "boundLiterals": {
            "B1Mb4CwnaV": "On Boot"
          },
          "id": "rktpKPZRN",
          "position": {
            "x": -1,
            "y": 2,
            "units": "slots"
          },
          "type": "@/set-measurement-timing-budget"
        },
        "ryn6y936N": {
          "id": "ryn6y936N",
          "position": {
            "x": -9,
            "y": 1,
            "units": "slots"
          },
          "type": "@/vl53l1x-device"
        },
        "rkGC3MIAw": {
          "id": "rkGC3MIAw",
          "type": "@/set-roi",
          "position": {
            "x": 2,
            "y": 1,
            "units": "slots"
          }
        },
        "S1eVaGI0v": {
          "id": "S1eVaGI0v",
          "label": "DEV",
          "position": {
            "x": 2,
            "y": 0,
            "units": "slots"
          },
          "type": "xod/patch-nodes/from-bus"
        },
        "rJEHaGLRD": {
          "id": "rJEHaGLRD",
          "type": "xod/patch-nodes/input-number",
          "position": {
            "x": 3,
            "y": 0,
            "units": "slots"
          },
          "label": "ROI-X",
          "description": "ROI width in single photon avalanche detectors (SPADs). Full width of sensor is 16 SPADS. Minimum width of ROI is 4 SPADs.",
          "boundLiterals": {
            "__out__": "16"
          }
        },
        "BJYBaGUAP": {
          "id": "BJYBaGUAP",
          "type": "xod/patch-nodes/input-number",
          "position": {
            "x": 4,
            "y": 0,
            "units": "slots"
          },
          "label": "ROI-Y",
          "description": "ROI height in single photon avalanche detectors (SPADs). Full height of sensor is 16 SPADS. Minimum height of ROI is 4 SPADs.",
          "boundLiterals": {
            "__out__": "16"
          }
        }
      },
      "path": "@/tof-sensor"
    },
    "@/vl53l1x-device": {
      "attachments": [
        {
          "filename": "patch.cpp",
          "encoding": "utf-8",
          "content": "// Tell XOD where it could download the library:\n#pragma XOD require \"https://github.com/WaylandM/vl53l1x-arduino-mtw\"\n\n//Include C++ libraries\n#include <VL53L1XMTW.h>\n#include <Wire.h>\n\nnode {\n    meta {\n        // Define our custom type as a pointer on the class instance.\n        using Type = VL53L1XMTW*;\n    }\n\n    // Create an object of the class VL53L1XMTW\n    VL53L1XMTW sensor = VL53L1XMTW();\n\n    void evaluate(Context ctx) {\n        // It should be evaluated only once on the first (setup) transaction\n        if (!isSettingUp())\n            return;\n\n        emitValue<output_DEV>(ctx, &sensor);\n    }\n}\n\n"
        }
      ],
      "description": "Create VL53L1X device.",
      "nodes": {
        "HJSAd3qp4": {
          "description": "A VL53L1X device.",
          "id": "HJSAd3qp4",
          "label": "DEV",
          "position": {
            "x": 0,
            "y": 2,
            "units": "slots"
          },
          "type": "xod/patch-nodes/output-self"
        },
        "Hkb3hFBpN": {
          "id": "Hkb3hFBpN",
          "position": {
            "x": 0,
            "y": 1,
            "units": "slots"
          },
          "type": "xod/patch-nodes/not-implemented-in-xod"
        }
      },
      "path": "@/vl53l1x-device"
    }
  },
  "version": "0.0.3"
}
